{
  "meta": {
    "name": "20.5x14E",
    "diameter_in": 20.5,
    "pitch_in": 14.0,
    "blades": 2,
    "type": [
      "Electric"
    ],
    "apc_name": "20.5x14E",
    "uiuc_name": null,
    "has_simulated": true,
    "has_empirical": false
  },
  "sources": {
    "simulated": {
      "rpm_min": 1000,
      "rpm_max": 11000,
      "v_max_mph": 178.7,
      "max_thrust_N": 309.1,
      "max_power_W": 14949.7,
      "sweep": [
        {
          "rpm": 1000.0,
          "V_mph": 0.0,
          "J": 0.0,
          "Ct": 0.0951,
          "Cp": 0.0387,
          "eff": 0.0,
          "thrust_N": 2.381,
          "power_W": 8.4,
          "torque_Nm": 0.08,
          "mach": 0.08
        },
        {
          "rpm": 1000.0,
          "V_mph": 0.56,
          "J": 0.0287,
          "Ct": 0.0941,
          "Cp": 0.0394,
          "eff": 0.0687,
          "thrust_N": 2.356,
          "power_W": 8.556,
          "torque_Nm": 0.082,
          "mach": 0.08
        },
        {
          "rpm": 1000.0,
          "V_mph": 1.12,
          "J": 0.0575,
          "Ct": 0.093,
          "Cp": 0.0401,
          "eff": 0.1333,
          "thrust_N": 2.328,
          "power_W": 8.711,
          "torque_Nm": 0.083,
          "mach": 0.08
        },
        {
          "rpm": 1000.0,
          "V_mph": 1.67,
          "J": 0.0862,
          "Ct": 0.0918,
          "Cp": 0.0408,
          "eff": 0.1939,
          "thrust_N": 2.297,
          "power_W": 8.863,
          "torque_Nm": 0.085,
          "mach": 0.08
        },
        {
          "rpm": 1000.0,
          "V_mph": 2.23,
          "J": 0.1149,
          "Ct": 0.0904,
          "Cp": 0.0415,
          "eff": 0.2505,
          "thrust_N": 2.262,
          "power_W": 9.008,
          "torque_Nm": 0.086,
          "mach": 0.08
        },
        {
          "rpm": 1000.0,
          "V_mph": 2.79,
          "J": 0.1437,
          "Ct": 0.0888,
          "Cp": 0.0421,
          "eff": 0.3033,
          "thrust_N": 2.224,
          "power_W": 9.144,
          "torque_Nm": 0.087,
          "mach": 0.08
        },
        {
          "rpm": 1000.0,
          "V_mph": 3.35,
          "J": 0.1724,
          "Ct": 0.0871,
          "Cp": 0.0427,
          "eff": 0.3523,
          "thrust_N": 2.182,
          "power_W": 9.267,
          "torque_Nm": 0.088,
          "mach": 0.08
        },
        {
          "rpm": 1000.0,
          "V_mph": 3.9,
          "J": 0.2012,
          "Ct": 0.0853,
          "Cp": 0.0431,
          "eff": 0.3976,
          "thrust_N": 2.135,
          "power_W": 9.373,
          "torque_Nm": 0.09,
          "mach": 0.08
        },
        {
          "rpm": 1000.0,
          "V_mph": 4.46,
          "J": 0.2299,
          "Ct": 0.0832,
          "Cp": 0.0435,
          "eff": 0.4395,
          "thrust_N": 2.083,
          "power_W": 9.458,
          "torque_Nm": 0.09,
          "mach": 0.08
        },
        {
          "rpm": 1000.0,
          "V_mph": 5.02,
          "J": 0.2586,
          "Ct": 0.081,
          "Cp": 0.0438,
          "eff": 0.478,
          "thrust_N": 2.027,
          "power_W": 9.518,
          "torque_Nm": 0.091,
          "mach": 0.08
        },
        {
          "rpm": 1000.0,
          "V_mph": 5.58,
          "J": 0.2874,
          "Ct": 0.0785,
          "Cp": 0.044,
          "eff": 0.5133,
          "thrust_N": 1.965,
          "power_W": 9.549,
          "torque_Nm": 0.091,
          "mach": 0.08
        },
        {
          "rpm": 1000.0,
          "V_mph": 6.14,
          "J": 0.3161,
          "Ct": 0.0758,
          "Cp": 0.0439,
          "eff": 0.5455,
          "thrust_N": 1.898,
          "power_W": 9.546,
          "torque_Nm": 0.091,
          "mach": 0.08
        },
        {
          "rpm": 1000.0,
          "V_mph": 6.69,
          "J": 0.3448,
          "Ct": 0.0729,
          "Cp": 0.0438,
          "eff": 0.5748,
          "thrust_N": 1.826,
          "power_W": 9.506,
          "torque_Nm": 0.091,
          "mach": 0.08
        },
        {
          "rpm": 1000.0,
          "V_mph": 7.25,
          "J": 0.3736,
          "Ct": 0.0698,
          "Cp": 0.0434,
          "eff": 0.6011,
          "thrust_N": 1.748,
          "power_W": 9.425,
          "torque_Nm": 0.09,
          "mach": 0.08
        },
        {
          "rpm": 1000.0,
          "V_mph": 7.81,
          "J": 0.4023,
          "Ct": 0.0665,
          "Cp": 0.0428,
          "eff": 0.6246,
          "thrust_N": 1.664,
          "power_W": 9.299,
          "torque_Nm": 0.089,
          "mach": 0.08
        },
        {
          "rpm": 1000.0,
          "V_mph": 8.37,
          "J": 0.431,
          "Ct": 0.0629,
          "Cp": 0.042,
          "eff": 0.6452,
          "thrust_N": 1.574,
          "power_W": 9.125,
          "torque_Nm": 0.087,
          "mach": 0.08
        },
        {
          "rpm": 1000.0,
          "V_mph": 8.93,
          "J": 0.4598,
          "Ct": 0.059,
          "Cp": 0.041,
          "eff": 0.6627,
          "thrust_N": 1.478,
          "power_W": 8.9,
          "torque_Nm": 0.085,
          "mach": 0.08
        },
        {
          "rpm": 1000.0,
          "V_mph": 9.48,
          "J": 0.4885,
          "Ct": 0.055,
          "Cp": 0.0397,
          "eff": 0.677,
          "thrust_N": 1.377,
          "power_W": 8.624,
          "torque_Nm": 0.082,
          "mach": 0.08
        },
        {
          "rpm": 1000.0,
          "V_mph": 10.04,
          "J": 0.5172,
          "Ct": 0.0508,
          "Cp": 0.0382,
          "eff": 0.6877,
          "thrust_N": 1.272,
          "power_W": 8.3,
          "torque_Nm": 0.079,
          "mach": 0.08
        },
        {
          "rpm": 1000.0,
          "V_mph": 10.6,
          "J": 0.546,
          "Ct": 0.0464,
          "Cp": 0.0365,
          "eff": 0.6944,
          "thrust_N": 1.162,
          "power_W": 7.931,
          "torque_Nm": 0.076,
          "mach": 0.08
        },
        {
          "rpm": 1000.0,
          "V_mph": 11.16,
          "J": 0.5747,
          "Ct": 0.0419,
          "Cp": 0.0346,
          "eff": 0.6964,
          "thrust_N": 1.05,
          "power_W": 7.518,
          "torque_Nm": 0.072,
          "mach": 0.08
        },
        {
          "rpm": 1000.0,
          "V_mph": 11.71,
          "J": 0.6035,
          "Ct": 0.0373,
          "Cp": 0.0325,
          "eff": 0.6927,
          "thrust_N": 0.935,
          "power_W": 7.065,
          "torque_Nm": 0.067,
          "mach": 0.08
        },
        {
          "rpm": 1000.0,
          "V_mph": 12.27,
          "J": 0.6322,
          "Ct": 0.0327,
          "Cp": 0.0303,
          "eff": 0.6822,
          "thrust_N": 0.817,
          "power_W": 6.573,
          "torque_Nm": 0.063,
          "mach": 0.08
        },
        {
          "rpm": 1000.0,
          "V_mph": 12.83,
          "J": 0.6609,
          "Ct": 0.0279,
          "Cp": 0.0278,
          "eff": 0.663,
          "thrust_N": 0.699,
          "power_W": 6.046,
          "torque_Nm": 0.058,
          "mach": 0.08
        },
        {
          "rpm": 1000.0,
          "V_mph": 13.39,
          "J": 0.6897,
          "Ct": 0.0232,
          "Cp": 0.0253,
          "eff": 0.6322,
          "thrust_N": 0.58,
          "power_W": 5.487,
          "torque_Nm": 0.052,
          "mach": 0.08
        },
        {
          "rpm": 1000.0,
          "V_mph": 13.95,
          "J": 0.7184,
          "Ct": 0.0184,
          "Cp": 0.0225,
          "eff": 0.5858,
          "thrust_N": 0.46,
          "power_W": 4.898,
          "torque_Nm": 0.047,
          "mach": 0.08
        },
        {
          "rpm": 1000.0,
          "V_mph": 14.5,
          "J": 0.7471,
          "Ct": 0.0136,
          "Cp": 0.0197,
          "eff": 0.5168,
          "thrust_N": 0.341,
          "power_W": 4.283,
          "torque_Nm": 0.041,
          "mach": 0.08
        },
        {
          "rpm": 1000.0,
          "V_mph": 15.06,
          "J": 0.7759,
          "Ct": 0.0089,
          "Cp": 0.0168,
          "eff": 0.4136,
          "thrust_N": 0.224,
          "power_W": 3.648,
          "torque_Nm": 0.035,
          "mach": 0.08
        },
        {
          "rpm": 1000.0,
          "V_mph": 15.62,
          "J": 0.8046,
          "Ct": 0.0043,
          "Cp": 0.0138,
          "eff": 0.2538,
          "thrust_N": 0.109,
          "power_W": 2.996,
          "torque_Nm": 0.029,
          "mach": 0.08
        },
        {
          "rpm": 1000.0,
          "V_mph": 16.18,
          "J": 0.8333,
          "Ct": -0.0001,
          "Cp": 0.0107,
          "eff": -0.0099,
          "thrust_N": -0.003,
          "power_W": 2.334,
          "torque_Nm": 0.022,
          "mach": 0.08
        },
        {
          "rpm": 2000.0,
          "V_mph": 0.0,
          "J": 0.0,
          "Ct": 0.0954,
          "Cp": 0.0361,
          "eff": 0.0,
          "thrust_N": 9.557,
          "power_W": 62.732,
          "torque_Nm": 0.3,
          "mach": 0.16
        },
        {
          "rpm": 2000.0,
          "V_mph": 1.12,
          "J": 0.0288,
          "Ct": 0.0945,
          "Cp": 0.0368,
          "eff": 0.0739,
          "thrust_N": 9.459,
          "power_W": 64.043,
          "torque_Nm": 0.306,
          "mach": 0.16
        },
        {
          "rpm": 2000.0,
          "V_mph": 2.24,
          "J": 0.0577,
          "Ct": 0.0934,
          "Cp": 0.0376,
          "eff": 0.1432,
          "thrust_N": 9.348,
          "power_W": 65.355,
          "torque_Nm": 0.312,
          "mach": 0.16
        },
        {
          "rpm": 2000.0,
          "V_mph": 3.36,
          "J": 0.0865,
          "Ct": 0.0921,
          "Cp": 0.0383,
          "eff": 0.2078,
          "thrust_N": 9.225,
          "power_W": 66.645,
          "torque_Nm": 0.318,
          "mach": 0.16
        },
        {
          "rpm": 2000.0,
          "V_mph": 4.48,
          "J": 0.1153,
          "Ct": 0.0907,
          "Cp": 0.0391,
          "eff": 0.2679,
          "thrust_N": 9.087,
          "power_W": 67.889,
          "torque_Nm": 0.324,
          "mach": 0.16
        },
        {
          "rpm": 2000.0,
          "V_mph": 5.6,
          "J": 0.1442,
          "Ct": 0.0892,
          "Cp": 0.0397,
          "eff": 0.3237,
          "thrust_N": 8.934,
          "power_W": 69.059,
          "torque_Nm": 0.33,
          "mach": 0.16
        },
        {
          "rpm": 2000.0,
          "V_mph": 6.72,
          "J": 0.173,
          "Ct": 0.0875,
          "Cp": 0.0403,
          "eff": 0.3753,
          "thrust_N": 8.765,
          "power_W": 70.126,
          "torque_Nm": 0.335,
          "mach": 0.16
        },
        {
          "rpm": 2000.0,
          "V_mph": 7.84,
          "J": 0.2018,
          "Ct": 0.0857,
          "Cp": 0.0409,
          "eff": 0.4228,
          "thrust_N": 8.578,
          "power_W": 71.059,
          "torque_Nm": 0.339,
          "mach": 0.16
        },
        {
          "rpm": 2000.0,
          "V_mph": 8.95,
          "J": 0.2306,
          "Ct": 0.0836,
          "Cp": 0.0413,
          "eff": 0.4666,
          "thrust_N": 8.371,
          "power_W": 71.823,
          "torque_Nm": 0.343,
          "mach": 0.16
        },
        {
          "rpm": 2000.0,
          "V_mph": 10.07,
          "J": 0.2595,
          "Ct": 0.0813,
          "Cp": 0.0416,
          "eff": 0.5067,
          "thrust_N": 8.145,
          "power_W": 72.385,
          "torque_Nm": 0.346,
          "mach": 0.16
        },
        {
          "rpm": 2000.0,
          "V_mph": 11.19,
          "J": 0.2883,
          "Ct": 0.0789,
          "Cp": 0.0418,
          "eff": 0.5435,
          "thrust_N": 7.897,
          "power_W": 72.709,
          "torque_Nm": 0.347,
          "mach": 0.16
        },
        {
          "rpm": 2000.0,
          "V_mph": 12.31,
          "J": 0.3171,
          "Ct": 0.0762,
          "Cp": 0.0419,
          "eff": 0.5771,
          "thrust_N": 7.628,
          "power_W": 72.761,
          "torque_Nm": 0.347,
          "mach": 0.16
        },
        {
          "rpm": 2000.0,
          "V_mph": 13.43,
          "J": 0.346,
          "Ct": 0.0733,
          "Cp": 0.0417,
          "eff": 0.6076,
          "thrust_N": 7.336,
          "power_W": 72.507,
          "torque_Nm": 0.346,
          "mach": 0.16
        },
        {
          "rpm": 2000.0,
          "V_mph": 14.55,
          "J": 0.3748,
          "Ct": 0.0701,
          "Cp": 0.0414,
          "eff": 0.6351,
          "thrust_N": 7.021,
          "power_W": 71.915,
          "torque_Nm": 0.343,
          "mach": 0.16
        },
        {
          "rpm": 2000.0,
          "V_mph": 15.67,
          "J": 0.4036,
          "Ct": 0.0667,
          "Cp": 0.0408,
          "eff": 0.6599,
          "thrust_N": 6.683,
          "power_W": 70.953,
          "torque_Nm": 0.339,
          "mach": 0.16
        },
        {
          "rpm": 2000.0,
          "V_mph": 16.79,
          "J": 0.4325,
          "Ct": 0.0631,
          "Cp": 0.04,
          "eff": 0.6818,
          "thrust_N": 6.321,
          "power_W": 69.591,
          "torque_Nm": 0.332,
          "mach": 0.16
        },
        {
          "rpm": 2000.0,
          "V_mph": 17.91,
          "J": 0.4613,
          "Ct": 0.0593,
          "Cp": 0.039,
          "eff": 0.7008,
          "thrust_N": 5.935,
          "power_W": 67.805,
          "torque_Nm": 0.324,
          "mach": 0.16
        },
        {
          "rpm": 2000.0,
          "V_mph": 19.03,
          "J": 0.4901,
          "Ct": 0.0552,
          "Cp": 0.0377,
          "eff": 0.717,
          "thrust_N": 5.528,
          "power_W": 65.595,
          "torque_Nm": 0.313,
          "mach": 0.16
        },
        {
          "rpm": 2000.0,
          "V_mph": 20.15,
          "J": 0.5189,
          "Ct": 0.051,
          "Cp": 0.0362,
          "eff": 0.7299,
          "thrust_N": 5.103,
          "power_W": 62.979,
          "torque_Nm": 0.301,
          "mach": 0.16
        },
        {
          "rpm": 2000.0,
          "V_mph": 21.27,
          "J": 0.5478,
          "Ct": 0.0466,
          "Cp": 0.0345,
          "eff": 0.7392,
          "thrust_N": 4.663,
          "power_W": 59.977,
          "torque_Nm": 0.286,
          "mach": 0.17
        },
        {
          "rpm": 2000.0,
          "V_mph": 22.39,
          "J": 0.5766,
          "Ct": 0.042,
          "Cp": 0.0326,
          "eff": 0.7443,
          "thrust_N": 4.21,
          "power_W": 56.608,
          "torque_Nm": 0.27,
          "mach": 0.17
        },
        {
          "rpm": 2000.0,
          "V_mph": 23.51,
          "J": 0.6054,
          "Ct": 0.0374,
          "Cp": 0.0304,
          "eff": 0.7445,
          "thrust_N": 3.747,
          "power_W": 52.891,
          "torque_Nm": 0.253,
          "mach": 0.17
        },
        {
          "rpm": 2000.0,
          "V_mph": 24.63,
          "J": 0.6343,
          "Ct": 0.0327,
          "Cp": 0.0281,
          "eff": 0.7385,
          "thrust_N": 3.277,
          "power_W": 48.845,
          "torque_Nm": 0.233,
          "mach": 0.17
        },
        {
          "rpm": 2000.0,
          "V_mph": 25.75,
          "J": 0.6631,
          "Ct": 0.028,
          "Cp": 0.0256,
          "eff": 0.7246,
          "thrust_N": 2.801,
          "power_W": 44.492,
          "torque_Nm": 0.212,
          "mach": 0.17
        },
        {
          "rpm": 2000.0,
          "V_mph": 26.86,
          "J": 0.6919,
          "Ct": 0.0232,
          "Cp": 0.0229,
          "eff": 0.7,
          "thrust_N": 2.323,
          "power_W": 39.855,
          "torque_Nm": 0.19,
          "mach": 0.17
        },
        {
          "rpm": 2000.0,
          "V_mph": 27.98,
          "J": 0.7208,
          "Ct": 0.0184,
          "Cp": 0.0201,
          "eff": 0.6602,
          "thrust_N": 1.845,
          "power_W": 34.964,
          "torque_Nm": 0.167,
          "mach": 0.17
        },
        {
          "rpm": 2000.0,
          "V_mph": 29.1,
          "J": 0.7496,
          "Ct": 0.0137,
          "Cp": 0.0172,
          "eff": 0.5973,
          "thrust_N": 1.37,
          "power_W": 29.849,
          "torque_Nm": 0.143,
          "mach": 0.17
        },
        {
          "rpm": 2000.0,
          "V_mph": 30.22,
          "J": 0.7784,
          "Ct": 0.009,
          "Cp": 0.0141,
          "eff": 0.4962,
          "thrust_N": 0.902,
          "power_W": 24.552,
          "torque_Nm": 0.117,
          "mach": 0.17
        },
        {
          "rpm": 2000.0,
          "V_mph": 31.34,
          "J": 0.8073,
          "Ct": 0.0044,
          "Cp": 0.011,
          "eff": 0.3246,
          "thrust_N": 0.443,
          "power_W": 19.115,
          "torque_Nm": 0.091,
          "mach": 0.17
        },
        {
          "rpm": 2000.0,
          "V_mph": 32.46,
          "J": 0.8361,
          "Ct": 0.0,
          "Cp": 0.0078,
          "eff": -0.0032,
          "thrust_N": -0.003,
          "power_W": 13.587,
          "torque_Nm": 0.065,
          "mach": 0.17
        },
        {
          "rpm": 3000.0,
          "V_mph": 0.0,
          "J": 0.0,
          "Ct": 0.0958,
          "Cp": 0.0351,
          "eff": 0.0,
          "thrust_N": 21.587,
          "power_W": 205.764,
          "torque_Nm": 0.655,
          "mach": 0.24
        },
        {
          "rpm": 3000.0,
          "V_mph": 1.68,
          "J": 0.0289,
          "Ct": 0.0948,
          "Cp": 0.0359,
          "eff": 0.0763,
          "thrust_N": 21.367,
          "power_W": 210.309,
          "torque_Nm": 0.669,
          "mach": 0.24
        },
        {
          "rpm": 3000.0,
          "V_mph": 3.36,
          "J": 0.0577,
          "Ct": 0.0937,
          "Cp": 0.0366,
          "eff": 0.1477,
          "thrust_N": 21.121,
          "power_W": 214.865,
          "torque_Nm": 0.684,
          "mach": 0.24
        },
        {
          "rpm": 3000.0,
          "V_mph": 5.04,
          "J": 0.0866,
          "Ct": 0.0925,
          "Cp": 0.0374,
          "eff": 0.2142,
          "thrust_N": 20.846,
          "power_W": 219.354,
          "torque_Nm": 0.698,
          "mach": 0.24
        },
        {
          "rpm": 3000.0,
          "V_mph": 6.72,
          "J": 0.1154,
          "Ct": 0.0912,
          "Cp": 0.0381,
          "eff": 0.276,
          "thrust_N": 20.539,
          "power_W": 223.693,
          "torque_Nm": 0.712,
          "mach": 0.24
        },
        {
          "rpm": 3000.0,
          "V_mph": 8.4,
          "J": 0.1443,
          "Ct": 0.0896,
          "Cp": 0.0388,
          "eff": 0.3331,
          "thrust_N": 20.197,
          "power_W": 227.789,
          "torque_Nm": 0.725,
          "mach": 0.24
        },
        {
          "rpm": 3000.0,
          "V_mph": 10.08,
          "J": 0.1732,
          "Ct": 0.088,
          "Cp": 0.0395,
          "eff": 0.3858,
          "thrust_N": 19.817,
          "power_W": 231.541,
          "torque_Nm": 0.737,
          "mach": 0.24
        },
        {
          "rpm": 3000.0,
          "V_mph": 11.77,
          "J": 0.202,
          "Ct": 0.0861,
          "Cp": 0.04,
          "eff": 0.4344,
          "thrust_N": 19.396,
          "power_W": 234.837,
          "torque_Nm": 0.748,
          "mach": 0.24
        },
        {
          "rpm": 3000.0,
          "V_mph": 13.45,
          "J": 0.2309,
          "Ct": 0.084,
          "Cp": 0.0405,
          "eff": 0.479,
          "thrust_N": 18.932,
          "power_W": 237.563,
          "torque_Nm": 0.756,
          "mach": 0.24
        },
        {
          "rpm": 3000.0,
          "V_mph": 15.13,
          "J": 0.2597,
          "Ct": 0.0818,
          "Cp": 0.0408,
          "eff": 0.52,
          "thrust_N": 18.423,
          "power_W": 239.6,
          "torque_Nm": 0.763,
          "mach": 0.24
        },
        {
          "rpm": 3000.0,
          "V_mph": 16.81,
          "J": 0.2886,
          "Ct": 0.0793,
          "Cp": 0.0411,
          "eff": 0.5574,
          "thrust_N": 17.865,
          "power_W": 240.826,
          "torque_Nm": 0.767,
          "mach": 0.24
        },
        {
          "rpm": 3000.0,
          "V_mph": 18.49,
          "J": 0.3175,
          "Ct": 0.0766,
          "Cp": 0.0411,
          "eff": 0.5916,
          "thrust_N": 17.258,
          "power_W": 241.121,
          "torque_Nm": 0.768,
          "mach": 0.25
        },
        {
          "rpm": 3000.0,
          "V_mph": 20.17,
          "J": 0.3463,
          "Ct": 0.0737,
          "Cp": 0.041,
          "eff": 0.6227,
          "thrust_N": 16.6,
          "power_W": 240.367,
          "torque_Nm": 0.765,
          "mach": 0.25
        },
        {
          "rpm": 3000.0,
          "V_mph": 21.85,
          "J": 0.3752,
          "Ct": 0.0705,
          "Cp": 0.0406,
          "eff": 0.6509,
          "thrust_N": 15.889,
          "power_W": 238.451,
          "torque_Nm": 0.759,
          "mach": 0.25
        },
        {
          "rpm": 3000.0,
          "V_mph": 23.53,
          "J": 0.404,
          "Ct": 0.0671,
          "Cp": 0.0401,
          "eff": 0.6762,
          "thrust_N": 15.124,
          "power_W": 235.266,
          "torque_Nm": 0.749,
          "mach": 0.25
        },
        {
          "rpm": 3000.0,
          "V_mph": 25.21,
          "J": 0.4329,
          "Ct": 0.0635,
          "Cp": 0.0393,
          "eff": 0.6989,
          "thrust_N": 14.306,
          "power_W": 230.705,
          "torque_Nm": 0.734,
          "mach": 0.25
        },
        {
          "rpm": 3000.0,
          "V_mph": 26.89,
          "J": 0.4618,
          "Ct": 0.0596,
          "Cp": 0.0383,
          "eff": 0.7188,
          "thrust_N": 13.433,
          "power_W": 224.677,
          "torque_Nm": 0.715,
          "mach": 0.25
        },
        {
          "rpm": 3000.0,
          "V_mph": 28.57,
          "J": 0.4906,
          "Ct": 0.0555,
          "Cp": 0.037,
          "eff": 0.7359,
          "thrust_N": 12.512,
          "power_W": 217.186,
          "torque_Nm": 0.691,
          "mach": 0.25
        },
        {
          "rpm": 3000.0,
          "V_mph": 30.25,
          "J": 0.5195,
          "Ct": 0.0513,
          "Cp": 0.0355,
          "eff": 0.75,
          "thrust_N": 11.55,
          "power_W": 208.286,
          "torque_Nm": 0.663,
          "mach": 0.25
        },
        {
          "rpm": 3000.0,
          "V_mph": 31.93,
          "J": 0.5483,
          "Ct": 0.0468,
          "Cp": 0.0338,
          "eff": 0.7608,
          "thrust_N": 10.553,
          "power_W": 198.041,
          "torque_Nm": 0.63,
          "mach": 0.25
        },
        {
          "rpm": 3000.0,
          "V_mph": 33.62,
          "J": 0.5772,
          "Ct": 0.0423,
          "Cp": 0.0318,
          "eff": 0.7677,
          "thrust_N": 9.529,
          "power_W": 186.515,
          "torque_Nm": 0.594,
          "mach": 0.25
        },
        {
          "rpm": 3000.0,
          "V_mph": 35.3,
          "J": 0.6061,
          "Ct": 0.0376,
          "Cp": 0.0296,
          "eff": 0.7701,
          "thrust_N": 8.481,
          "power_W": 173.771,
          "torque_Nm": 0.553,
          "mach": 0.25
        },
        {
          "rpm": 3000.0,
          "V_mph": 36.98,
          "J": 0.6349,
          "Ct": 0.0329,
          "Cp": 0.0273,
          "eff": 0.7669,
          "thrust_N": 7.417,
          "power_W": 159.876,
          "torque_Nm": 0.509,
          "mach": 0.25
        },
        {
          "rpm": 3000.0,
          "V_mph": 38.66,
          "J": 0.6638,
          "Ct": 0.0281,
          "Cp": 0.0247,
          "eff": 0.7563,
          "thrust_N": 6.341,
          "power_W": 144.902,
          "torque_Nm": 0.461,
          "mach": 0.25
        },
        {
          "rpm": 3000.0,
          "V_mph": 40.34,
          "J": 0.6926,
          "Ct": 0.0233,
          "Cp": 0.022,
          "eff": 0.7357,
          "thrust_N": 5.26,
          "power_W": 128.934,
          "torque_Nm": 0.41,
          "mach": 0.25
        },
        {
          "rpm": 3000.0,
          "V_mph": 42.02,
          "J": 0.7215,
          "Ct": 0.0186,
          "Cp": 0.0191,
          "eff": 0.7007,
          "thrust_N": 4.18,
          "power_W": 112.068,
          "torque_Nm": 0.357,
          "mach": 0.25
        },
        {
          "rpm": 3000.0,
          "V_mph": 43.7,
          "J": 0.7504,
          "Ct": 0.0138,
          "Cp": 0.0161,
          "eff": 0.643,
          "thrust_N": 3.108,
          "power_W": 94.42,
          "torque_Nm": 0.301,
          "mach": 0.25
        },
        {
          "rpm": 3000.0,
          "V_mph": 45.38,
          "J": 0.7792,
          "Ct": 0.0091,
          "Cp": 0.013,
          "eff": 0.5462,
          "thrust_N": 2.05,
          "power_W": 76.127,
          "torque_Nm": 0.242,
          "mach": 0.25
        },
        {
          "rpm": 3000.0,
          "V_mph": 47.06,
          "J": 0.8081,
          "Ct": 0.0045,
          "Cp": 0.0098,
          "eff": 0.3721,
          "thrust_N": 1.014,
          "power_W": 57.348,
          "torque_Nm": 0.183,
          "mach": 0.25
        },
        {
          "rpm": 3000.0,
          "V_mph": 48.74,
          "J": 0.8369,
          "Ct": 0.0,
          "Cp": 0.0065,
          "eff": 0.0049,
          "thrust_N": 0.009,
          "power_W": 38.244,
          "torque_Nm": 0.122,
          "mach": 0.25
        },
        {
          "rpm": 4000.0,
          "V_mph": 0.0,
          "J": 0.0,
          "Ct": 0.0963,
          "Cp": 0.0346,
          "eff": 0.0,
          "thrust_N": 38.559,
          "power_W": 481.275,
          "torque_Nm": 1.149,
          "mach": 0.33
        },
        {
          "rpm": 4000.0,
          "V_mph": 2.24,
          "J": 0.0289,
          "Ct": 0.0953,
          "Cp": 0.0354,
          "eff": 0.0778,
          "thrust_N": 38.174,
          "power_W": 492.287,
          "torque_Nm": 1.175,
          "mach": 0.33
        },
        {
          "rpm": 4000.0,
          "V_mph": 4.49,
          "J": 0.0578,
          "Ct": 0.0942,
          "Cp": 0.0362,
          "eff": 0.1504,
          "thrust_N": 37.743,
          "power_W": 503.34,
          "torque_Nm": 1.202,
          "mach": 0.33
        },
        {
          "rpm": 4000.0,
          "V_mph": 6.73,
          "J": 0.0867,
          "Ct": 0.093,
          "Cp": 0.037,
          "eff": 0.218,
          "thrust_N": 37.259,
          "power_W": 514.249,
          "torque_Nm": 1.228,
          "mach": 0.33
        },
        {
          "rpm": 4000.0,
          "V_mph": 8.98,
          "J": 0.1156,
          "Ct": 0.0917,
          "Cp": 0.0377,
          "eff": 0.2807,
          "thrust_N": 36.718,
          "power_W": 524.811,
          "torque_Nm": 1.253,
          "mach": 0.33
        },
        {
          "rpm": 4000.0,
          "V_mph": 11.22,
          "J": 0.1445,
          "Ct": 0.0902,
          "Cp": 0.0385,
          "eff": 0.3387,
          "thrust_N": 36.114,
          "power_W": 534.803,
          "torque_Nm": 1.277,
          "mach": 0.33
        },
        {
          "rpm": 4000.0,
          "V_mph": 13.46,
          "J": 0.1734,
          "Ct": 0.0885,
          "Cp": 0.0391,
          "eff": 0.3921,
          "thrust_N": 35.442,
          "power_W": 543.974,
          "torque_Nm": 1.299,
          "mach": 0.33
        },
        {
          "rpm": 4000.0,
          "V_mph": 15.71,
          "J": 0.2023,
          "Ct": 0.0866,
          "Cp": 0.0397,
          "eff": 0.4413,
          "thrust_N": 34.697,
          "power_W": 552.06,
          "torque_Nm": 1.318,
          "mach": 0.33
        },
        {
          "rpm": 4000.0,
          "V_mph": 17.95,
          "J": 0.2312,
          "Ct": 0.0846,
          "Cp": 0.0402,
          "eff": 0.4865,
          "thrust_N": 33.873,
          "power_W": 558.78,
          "torque_Nm": 1.334,
          "mach": 0.33
        },
        {
          "rpm": 4000.0,
          "V_mph": 20.19,
          "J": 0.2601,
          "Ct": 0.0823,
          "Cp": 0.0406,
          "eff": 0.5278,
          "thrust_N": 32.967,
          "power_W": 563.845,
          "torque_Nm": 1.346,
          "mach": 0.33
        },
        {
          "rpm": 4000.0,
          "V_mph": 22.44,
          "J": 0.289,
          "Ct": 0.0798,
          "Cp": 0.0408,
          "eff": 0.5657,
          "thrust_N": 31.974,
          "power_W": 566.958,
          "torque_Nm": 1.354,
          "mach": 0.33
        },
        {
          "rpm": 4000.0,
          "V_mph": 24.68,
          "J": 0.3179,
          "Ct": 0.0771,
          "Cp": 0.0408,
          "eff": 0.6003,
          "thrust_N": 30.891,
          "power_W": 567.828,
          "torque_Nm": 1.356,
          "mach": 0.33
        },
        {
          "rpm": 4000.0,
          "V_mph": 26.93,
          "J": 0.3467,
          "Ct": 0.0742,
          "Cp": 0.0407,
          "eff": 0.6318,
          "thrust_N": 29.716,
          "power_W": 566.167,
          "torque_Nm": 1.352,
          "mach": 0.33
        },
        {
          "rpm": 4000.0,
          "V_mph": 29.17,
          "J": 0.3756,
          "Ct": 0.071,
          "Cp": 0.0404,
          "eff": 0.6604,
          "thrust_N": 28.445,
          "power_W": 561.699,
          "torque_Nm": 1.341,
          "mach": 0.33
        },
        {
          "rpm": 4000.0,
          "V_mph": 31.41,
          "J": 0.4045,
          "Ct": 0.0676,
          "Cp": 0.0399,
          "eff": 0.6862,
          "thrust_N": 27.078,
          "power_W": 554.168,
          "torque_Nm": 1.323,
          "mach": 0.33
        },
        {
          "rpm": 4000.0,
          "V_mph": 33.66,
          "J": 0.4334,
          "Ct": 0.0639,
          "Cp": 0.0391,
          "eff": 0.7093,
          "thrust_N": 25.612,
          "power_W": 543.306,
          "torque_Nm": 1.297,
          "mach": 0.33
        },
        {
          "rpm": 4000.0,
          "V_mph": 35.9,
          "J": 0.4623,
          "Ct": 0.06,
          "Cp": 0.038,
          "eff": 0.7298,
          "thrust_N": 24.05,
          "power_W": 528.897,
          "torque_Nm": 1.263,
          "mach": 0.33
        },
        {
          "rpm": 4000.0,
          "V_mph": 38.14,
          "J": 0.4912,
          "Ct": 0.0559,
          "Cp": 0.0367,
          "eff": 0.7476,
          "thrust_N": 22.399,
          "power_W": 510.938,
          "torque_Nm": 1.22,
          "mach": 0.33
        },
        {
          "rpm": 4000.0,
          "V_mph": 40.39,
          "J": 0.5201,
          "Ct": 0.0516,
          "Cp": 0.0352,
          "eff": 0.7625,
          "thrust_N": 20.674,
          "power_W": 489.557,
          "torque_Nm": 1.169,
          "mach": 0.33
        },
        {
          "rpm": 4000.0,
          "V_mph": 42.63,
          "J": 0.549,
          "Ct": 0.0472,
          "Cp": 0.0334,
          "eff": 0.7743,
          "thrust_N": 18.887,
          "power_W": 464.904,
          "torque_Nm": 1.11,
          "mach": 0.33
        },
        {
          "rpm": 4000.0,
          "V_mph": 44.88,
          "J": 0.5779,
          "Ct": 0.0426,
          "Cp": 0.0314,
          "eff": 0.7824,
          "thrust_N": 17.049,
          "power_W": 437.129,
          "torque_Nm": 1.044,
          "mach": 0.33
        },
        {
          "rpm": 4000.0,
          "V_mph": 47.12,
          "J": 0.6068,
          "Ct": 0.0379,
          "Cp": 0.0292,
          "eff": 0.7863,
          "thrust_N": 15.17,
          "power_W": 406.386,
          "torque_Nm": 0.97,
          "mach": 0.33
        },
        {
          "rpm": 4000.0,
          "V_mph": 49.36,
          "J": 0.6357,
          "Ct": 0.0331,
          "Cp": 0.0268,
          "eff": 0.7849,
          "thrust_N": 13.261,
          "power_W": 372.832,
          "torque_Nm": 0.89,
          "mach": 0.33
        },
        {
          "rpm": 4000.0,
          "V_mph": 51.61,
          "J": 0.6646,
          "Ct": 0.0283,
          "Cp": 0.0242,
          "eff": 0.7766,
          "thrust_N": 11.332,
          "power_W": 336.646,
          "torque_Nm": 0.804,
          "mach": 0.33
        },
        {
          "rpm": 4000.0,
          "V_mph": 53.85,
          "J": 0.6935,
          "Ct": 0.0235,
          "Cp": 0.0214,
          "eff": 0.7588,
          "thrust_N": 9.394,
          "power_W": 298.031,
          "torque_Nm": 0.711,
          "mach": 0.33
        },
        {
          "rpm": 4000.0,
          "V_mph": 56.1,
          "J": 0.7224,
          "Ct": 0.0186,
          "Cp": 0.0185,
          "eff": 0.727,
          "thrust_N": 7.457,
          "power_W": 257.225,
          "torque_Nm": 0.614,
          "mach": 0.33
        },
        {
          "rpm": 4000.0,
          "V_mph": 58.34,
          "J": 0.7513,
          "Ct": 0.0138,
          "Cp": 0.0154,
          "eff": 0.6729,
          "thrust_N": 5.534,
          "power_W": 214.512,
          "torque_Nm": 0.512,
          "mach": 0.33
        },
        {
          "rpm": 4000.0,
          "V_mph": 60.58,
          "J": 0.7802,
          "Ct": 0.0091,
          "Cp": 0.0122,
          "eff": 0.5789,
          "thrust_N": 3.639,
          "power_W": 170.229,
          "torque_Nm": 0.406,
          "mach": 0.34
        },
        {
          "rpm": 4000.0,
          "V_mph": 62.83,
          "J": 0.8091,
          "Ct": 0.0045,
          "Cp": 0.009,
          "eff": 0.4017,
          "thrust_N": 1.784,
          "power_W": 124.77,
          "torque_Nm": 0.298,
          "mach": 0.34
        },
        {
          "rpm": 4000.0,
          "V_mph": 65.07,
          "J": 0.838,
          "Ct": 0.0,
          "Cp": 0.0056,
          "eff": -0.0059,
          "thrust_N": -0.016,
          "power_W": 78.519,
          "torque_Nm": 0.187,
          "mach": 0.34
        },
        {
          "rpm": 5000.0,
          "V_mph": 0.0,
          "J": 0.0,
          "Ct": 0.0968,
          "Cp": 0.0344,
          "eff": 0.0,
          "thrust_N": 60.603,
          "power_W": 935.564,
          "torque_Nm": 1.787,
          "mach": 0.41
        },
        {
          "rpm": 5000.0,
          "V_mph": 2.8,
          "J": 0.0289,
          "Ct": 0.0959,
          "Cp": 0.0353,
          "eff": 0.0786,
          "thrust_N": 60.016,
          "power_W": 957.507,
          "torque_Nm": 1.829,
          "mach": 0.41
        },
        {
          "rpm": 5000.0,
          "V_mph": 5.61,
          "J": 0.0578,
          "Ct": 0.0948,
          "Cp": 0.0361,
          "eff": 0.1519,
          "thrust_N": 59.355,
          "power_W": 979.563,
          "torque_Nm": 1.871,
          "mach": 0.41
        },
        {
          "rpm": 5000.0,
          "V_mph": 8.41,
          "J": 0.0867,
          "Ct": 0.0937,
          "Cp": 0.0369,
          "eff": 0.2201,
          "thrust_N": 58.613,
          "power_W": 1001.365,
          "torque_Nm": 1.912,
          "mach": 0.41
        },
        {
          "rpm": 5000.0,
          "V_mph": 11.22,
          "J": 0.1156,
          "Ct": 0.0923,
          "Cp": 0.0377,
          "eff": 0.2833,
          "thrust_N": 57.78,
          "power_W": 1022.508,
          "torque_Nm": 1.953,
          "mach": 0.41
        },
        {
          "rpm": 5000.0,
          "V_mph": 14.02,
          "J": 0.1444,
          "Ct": 0.0908,
          "Cp": 0.0384,
          "eff": 0.3418,
          "thrust_N": 56.848,
          "power_W": 1042.547,
          "torque_Nm": 1.991,
          "mach": 0.41
        },
        {
          "rpm": 5000.0,
          "V_mph": 16.82,
          "J": 0.1733,
          "Ct": 0.0892,
          "Cp": 0.0391,
          "eff": 0.3956,
          "thrust_N": 55.808,
          "power_W": 1060.982,
          "torque_Nm": 2.026,
          "mach": 0.41
        },
        {
          "rpm": 5000.0,
          "V_mph": 19.63,
          "J": 0.2022,
          "Ct": 0.0873,
          "Cp": 0.0397,
          "eff": 0.4452,
          "thrust_N": 54.652,
          "power_W": 1077.284,
          "torque_Nm": 2.057,
          "mach": 0.41
        },
        {
          "rpm": 5000.0,
          "V_mph": 22.43,
          "J": 0.2311,
          "Ct": 0.0853,
          "Cp": 0.0402,
          "eff": 0.4906,
          "thrust_N": 53.371,
          "power_W": 1090.892,
          "torque_Nm": 2.083,
          "mach": 0.41
        },
        {
          "rpm": 5000.0,
          "V_mph": 25.24,
          "J": 0.26,
          "Ct": 0.083,
          "Cp": 0.0406,
          "eff": 0.5323,
          "thrust_N": 51.959,
          "power_W": 1101.226,
          "torque_Nm": 2.103,
          "mach": 0.41
        },
        {
          "rpm": 5000.0,
          "V_mph": 28.04,
          "J": 0.2889,
          "Ct": 0.0805,
          "Cp": 0.0408,
          "eff": 0.5705,
          "thrust_N": 50.41,
          "power_W": 1107.7,
          "torque_Nm": 2.116,
          "mach": 0.41
        },
        {
          "rpm": 5000.0,
          "V_mph": 30.85,
          "J": 0.3178,
          "Ct": 0.0778,
          "Cp": 0.0409,
          "eff": 0.6053,
          "thrust_N": 48.716,
          "power_W": 1109.723,
          "torque_Nm": 2.119,
          "mach": 0.41
        },
        {
          "rpm": 5000.0,
          "V_mph": 33.65,
          "J": 0.3467,
          "Ct": 0.0749,
          "Cp": 0.0408,
          "eff": 0.6371,
          "thrust_N": 46.875,
          "power_W": 1106.722,
          "torque_Nm": 2.114,
          "mach": 0.41
        },
        {
          "rpm": 5000.0,
          "V_mph": 36.45,
          "J": 0.3756,
          "Ct": 0.0717,
          "Cp": 0.0404,
          "eff": 0.6661,
          "thrust_N": 44.883,
          "power_W": 1098.151,
          "torque_Nm": 2.097,
          "mach": 0.41
        },
        {
          "rpm": 5000.0,
          "V_mph": 39.26,
          "J": 0.4045,
          "Ct": 0.0683,
          "Cp": 0.0399,
          "eff": 0.6922,
          "thrust_N": 42.737,
          "power_W": 1083.491,
          "torque_Nm": 2.069,
          "mach": 0.41
        },
        {
          "rpm": 5000.0,
          "V_mph": 42.06,
          "J": 0.4333,
          "Ct": 0.0646,
          "Cp": 0.0391,
          "eff": 0.7158,
          "thrust_N": 40.435,
          "power_W": 1062.217,
          "torque_Nm": 2.029,
          "mach": 0.41
        },
        {
          "rpm": 5000.0,
          "V_mph": 44.87,
          "J": 0.4622,
          "Ct": 0.0607,
          "Cp": 0.0381,
          "eff": 0.7367,
          "thrust_N": 37.977,
          "power_W": 1033.883,
          "torque_Nm": 1.975,
          "mach": 0.41
        },
        {
          "rpm": 5000.0,
          "V_mph": 47.67,
          "J": 0.4911,
          "Ct": 0.0565,
          "Cp": 0.0368,
          "eff": 0.7551,
          "thrust_N": 35.379,
          "power_W": 998.465,
          "torque_Nm": 1.907,
          "mach": 0.41
        },
        {
          "rpm": 5000.0,
          "V_mph": 50.47,
          "J": 0.52,
          "Ct": 0.0522,
          "Cp": 0.0352,
          "eff": 0.7707,
          "thrust_N": 32.662,
          "power_W": 956.204,
          "torque_Nm": 1.826,
          "mach": 0.41
        },
        {
          "rpm": 5000.0,
          "V_mph": 53.28,
          "J": 0.5489,
          "Ct": 0.0477,
          "Cp": 0.0334,
          "eff": 0.7834,
          "thrust_N": 29.845,
          "power_W": 907.397,
          "torque_Nm": 1.733,
          "mach": 0.41
        },
        {
          "rpm": 5000.0,
          "V_mph": 56.08,
          "J": 0.5778,
          "Ct": 0.0431,
          "Cp": 0.0314,
          "eff": 0.7926,
          "thrust_N": 26.946,
          "power_W": 852.34,
          "torque_Nm": 1.628,
          "mach": 0.41
        },
        {
          "rpm": 5000.0,
          "V_mph": 58.89,
          "J": 0.6067,
          "Ct": 0.0383,
          "Cp": 0.0291,
          "eff": 0.7978,
          "thrust_N": 23.982,
          "power_W": 791.331,
          "torque_Nm": 1.511,
          "mach": 0.41
        },
        {
          "rpm": 5000.0,
          "V_mph": 61.69,
          "J": 0.6356,
          "Ct": 0.0335,
          "Cp": 0.0267,
          "eff": 0.798,
          "thrust_N": 20.969,
          "power_W": 724.69,
          "torque_Nm": 1.384,
          "mach": 0.41
        },
        {
          "rpm": 5000.0,
          "V_mph": 64.5,
          "J": 0.6645,
          "Ct": 0.0286,
          "Cp": 0.024,
          "eff": 0.7917,
          "thrust_N": 17.924,
          "power_W": 652.767,
          "torque_Nm": 1.247,
          "mach": 0.42
        },
        {
          "rpm": 5000.0,
          "V_mph": 67.3,
          "J": 0.6933,
          "Ct": 0.0237,
          "Cp": 0.0212,
          "eff": 0.7763,
          "thrust_N": 14.863,
          "power_W": 575.969,
          "torque_Nm": 1.1,
          "mach": 0.42
        },
        {
          "rpm": 5000.0,
          "V_mph": 70.1,
          "J": 0.7222,
          "Ct": 0.0189,
          "Cp": 0.0182,
          "eff": 0.7477,
          "thrust_N": 11.804,
          "power_W": 494.772,
          "torque_Nm": 0.945,
          "mach": 0.42
        },
        {
          "rpm": 5000.0,
          "V_mph": 72.91,
          "J": 0.7511,
          "Ct": 0.014,
          "Cp": 0.0151,
          "eff": 0.6973,
          "thrust_N": 8.767,
          "power_W": 409.747,
          "torque_Nm": 0.783,
          "mach": 0.42
        },
        {
          "rpm": 5000.0,
          "V_mph": 75.71,
          "J": 0.78,
          "Ct": 0.0092,
          "Cp": 0.0118,
          "eff": 0.6076,
          "thrust_N": 5.772,
          "power_W": 321.571,
          "torque_Nm": 0.614,
          "mach": 0.42
        },
        {
          "rpm": 5000.0,
          "V_mph": 78.52,
          "J": 0.8089,
          "Ct": 0.0045,
          "Cp": 0.0085,
          "eff": 0.432,
          "thrust_N": 2.844,
          "power_W": 231.038,
          "torque_Nm": 0.441,
          "mach": 0.42
        },
        {
          "rpm": 5000.0,
          "V_mph": 81.32,
          "J": 0.8378,
          "Ct": 0.0,
          "Cp": 0.0051,
          "eff": 0.0001,
          "thrust_N": 0.0,
          "power_W": 138.917,
          "torque_Nm": 0.265,
          "mach": 0.42
        },
        {
          "rpm": 6000.0,
          "V_mph": 0.0,
          "J": 0.0,
          "Ct": 0.0975,
          "Cp": 0.0345,
          "eff": 0.0,
          "thrust_N": 87.894,
          "power_W": 1618.912,
          "torque_Nm": 2.577,
          "mach": 0.49
        },
        {
          "rpm": 6000.0,
          "V_mph": 3.36,
          "J": 0.0289,
          "Ct": 0.0966,
          "Cp": 0.0353,
          "eff": 0.079,
          "thrust_N": 87.074,
          "power_W": 1657.673,
          "torque_Nm": 2.638,
          "mach": 0.49
        },
        {
          "rpm": 6000.0,
          "V_mph": 6.73,
          "J": 0.0578,
          "Ct": 0.0956,
          "Cp": 0.0362,
          "eff": 0.1527,
          "thrust_N": 86.148,
          "power_W": 1696.697,
          "torque_Nm": 2.7,
          "mach": 0.49
        },
        {
          "rpm": 6000.0,
          "V_mph": 10.09,
          "J": 0.0867,
          "Ct": 0.0944,
          "Cp": 0.037,
          "eff": 0.2213,
          "thrust_N": 85.104,
          "power_W": 1735.33,
          "torque_Nm": 2.762,
          "mach": 0.49
        },
        {
          "rpm": 6000.0,
          "V_mph": 13.46,
          "J": 0.1156,
          "Ct": 0.0931,
          "Cp": 0.0378,
          "eff": 0.2848,
          "thrust_N": 83.928,
          "power_W": 1772.863,
          "torque_Nm": 2.822,
          "mach": 0.49
        },
        {
          "rpm": 6000.0,
          "V_mph": 16.82,
          "J": 0.1444,
          "Ct": 0.0917,
          "Cp": 0.0385,
          "eff": 0.3435,
          "thrust_N": 82.607,
          "power_W": 1808.499,
          "torque_Nm": 2.878,
          "mach": 0.49
        },
        {
          "rpm": 6000.0,
          "V_mph": 20.19,
          "J": 0.1733,
          "Ct": 0.09,
          "Cp": 0.0392,
          "eff": 0.3976,
          "thrust_N": 81.129,
          "power_W": 1841.351,
          "torque_Nm": 2.931,
          "mach": 0.49
        },
        {
          "rpm": 6000.0,
          "V_mph": 23.55,
          "J": 0.2022,
          "Ct": 0.0882,
          "Cp": 0.0399,
          "eff": 0.4474,
          "thrust_N": 79.479,
          "power_W": 1870.481,
          "torque_Nm": 2.977,
          "mach": 0.49
        },
        {
          "rpm": 6000.0,
          "V_mph": 26.92,
          "J": 0.2311,
          "Ct": 0.0862,
          "Cp": 0.0404,
          "eff": 0.4931,
          "thrust_N": 77.647,
          "power_W": 1894.886,
          "torque_Nm": 3.016,
          "mach": 0.49
        },
        {
          "rpm": 6000.0,
          "V_mph": 30.28,
          "J": 0.26,
          "Ct": 0.0839,
          "Cp": 0.0408,
          "eff": 0.535,
          "thrust_N": 75.622,
          "power_W": 1913.542,
          "torque_Nm": 3.045,
          "mach": 0.49
        },
        {
          "rpm": 6000.0,
          "V_mph": 33.65,
          "J": 0.2889,
          "Ct": 0.0814,
          "Cp": 0.041,
          "eff": 0.5734,
          "thrust_N": 73.393,
          "power_W": 1925.399,
          "torque_Nm": 3.064,
          "mach": 0.49
        },
        {
          "rpm": 6000.0,
          "V_mph": 37.01,
          "J": 0.3178,
          "Ct": 0.0787,
          "Cp": 0.0411,
          "eff": 0.6085,
          "thrust_N": 70.953,
          "power_W": 1929.416,
          "torque_Nm": 3.071,
          "mach": 0.49
        },
        {
          "rpm": 6000.0,
          "V_mph": 40.38,
          "J": 0.3467,
          "Ct": 0.0758,
          "Cp": 0.041,
          "eff": 0.6405,
          "thrust_N": 68.294,
          "power_W": 1924.573,
          "torque_Nm": 3.063,
          "mach": 0.49
        },
        {
          "rpm": 6000.0,
          "V_mph": 43.74,
          "J": 0.3755,
          "Ct": 0.0726,
          "Cp": 0.0407,
          "eff": 0.6697,
          "thrust_N": 65.411,
          "power_W": 1909.9,
          "torque_Nm": 3.04,
          "mach": 0.49
        },
        {
          "rpm": 6000.0,
          "V_mph": 47.11,
          "J": 0.4044,
          "Ct": 0.0691,
          "Cp": 0.0402,
          "eff": 0.6962,
          "thrust_N": 62.302,
          "power_W": 1884.481,
          "torque_Nm": 2.999,
          "mach": 0.49
        },
        {
          "rpm": 6000.0,
          "V_mph": 50.47,
          "J": 0.4333,
          "Ct": 0.0654,
          "Cp": 0.0394,
          "eff": 0.7201,
          "thrust_N": 58.963,
          "power_W": 1847.399,
          "torque_Nm": 2.94,
          "mach": 0.49
        },
        {
          "rpm": 6000.0,
          "V_mph": 53.84,
          "J": 0.4622,
          "Ct": 0.0615,
          "Cp": 0.0383,
          "eff": 0.7415,
          "thrust_N": 55.393,
          "power_W": 1797.847,
          "torque_Nm": 2.861,
          "mach": 0.49
        },
        {
          "rpm": 6000.0,
          "V_mph": 57.2,
          "J": 0.4911,
          "Ct": 0.0573,
          "Cp": 0.037,
          "eff": 0.7604,
          "thrust_N": 51.616,
          "power_W": 1735.743,
          "torque_Nm": 2.763,
          "mach": 0.49
        },
        {
          "rpm": 6000.0,
          "V_mph": 60.57,
          "J": 0.52,
          "Ct": 0.0529,
          "Cp": 0.0354,
          "eff": 0.7766,
          "thrust_N": 47.66,
          "power_W": 1661.504,
          "torque_Nm": 2.644,
          "mach": 0.49
        },
        {
          "rpm": 6000.0,
          "V_mph": 63.93,
          "J": 0.5489,
          "Ct": 0.0483,
          "Cp": 0.0336,
          "eff": 0.79,
          "thrust_N": 43.556,
          "power_W": 1575.646,
          "torque_Nm": 2.508,
          "mach": 0.5
        },
        {
          "rpm": 6000.0,
          "V_mph": 67.3,
          "J": 0.5778,
          "Ct": 0.0436,
          "Cp": 0.0315,
          "eff": 0.8001,
          "thrust_N": 39.329,
          "power_W": 1478.693,
          "torque_Nm": 2.353,
          "mach": 0.5
        },
        {
          "rpm": 6000.0,
          "V_mph": 70.66,
          "J": 0.6066,
          "Ct": 0.0388,
          "Cp": 0.0292,
          "eff": 0.8064,
          "thrust_N": 35.005,
          "power_W": 1371.173,
          "torque_Nm": 2.182,
          "mach": 0.5
        },
        {
          "rpm": 6000.0,
          "V_mph": 74.02,
          "J": 0.6355,
          "Ct": 0.034,
          "Cp": 0.0267,
          "eff": 0.8079,
          "thrust_N": 30.608,
          "power_W": 1253.646,
          "torque_Nm": 1.995,
          "mach": 0.5
        },
        {
          "rpm": 6000.0,
          "V_mph": 77.39,
          "J": 0.6644,
          "Ct": 0.029,
          "Cp": 0.024,
          "eff": 0.8033,
          "thrust_N": 26.161,
          "power_W": 1126.738,
          "torque_Nm": 1.793,
          "mach": 0.5
        },
        {
          "rpm": 6000.0,
          "V_mph": 80.75,
          "J": 0.6933,
          "Ct": 0.0241,
          "Cp": 0.0211,
          "eff": 0.79,
          "thrust_N": 21.69,
          "power_W": 991.167,
          "torque_Nm": 1.577,
          "mach": 0.5
        },
        {
          "rpm": 6000.0,
          "V_mph": 84.12,
          "J": 0.7222,
          "Ct": 0.0191,
          "Cp": 0.0181,
          "eff": 0.7639,
          "thrust_N": 17.221,
          "power_W": 847.782,
          "torque_Nm": 1.349,
          "mach": 0.5
        },
        {
          "rpm": 6000.0,
          "V_mph": 87.48,
          "J": 0.7511,
          "Ct": 0.0142,
          "Cp": 0.0149,
          "eff": 0.7166,
          "thrust_N": 12.783,
          "power_W": 697.599,
          "torque_Nm": 1.11,
          "mach": 0.5
        },
        {
          "rpm": 6000.0,
          "V_mph": 90.85,
          "J": 0.78,
          "Ct": 0.0093,
          "Cp": 0.0115,
          "eff": 0.6301,
          "thrust_N": 8.407,
          "power_W": 541.827,
          "torque_Nm": 0.862,
          "mach": 0.5
        },
        {
          "rpm": 6000.0,
          "V_mph": 94.21,
          "J": 0.8089,
          "Ct": 0.0046,
          "Cp": 0.0081,
          "eff": 0.4551,
          "thrust_N": 4.127,
          "power_W": 381.892,
          "torque_Nm": 0.608,
          "mach": 0.5
        },
        {
          "rpm": 6000.0,
          "V_mph": 97.58,
          "J": 0.8377,
          "Ct": 0.0,
          "Cp": 0.0047,
          "eff": -0.0057,
          "thrust_N": -0.029,
          "power_W": 219.139,
          "torque_Nm": 0.349,
          "mach": 0.5
        },
        {
          "rpm": 7000.0,
          "V_mph": 0.0,
          "J": 0.0,
          "Ct": 0.0984,
          "Cp": 0.0347,
          "eff": 0.0,
          "thrust_N": 120.651,
          "power_W": 2587.362,
          "torque_Nm": 3.53,
          "mach": 0.57
        },
        {
          "rpm": 7000.0,
          "V_mph": 3.92,
          "J": 0.0289,
          "Ct": 0.0975,
          "Cp": 0.0356,
          "eff": 0.0791,
          "thrust_N": 119.582,
          "power_W": 2650.454,
          "torque_Nm": 3.616,
          "mach": 0.57
        },
        {
          "rpm": 7000.0,
          "V_mph": 7.85,
          "J": 0.0577,
          "Ct": 0.0965,
          "Cp": 0.0364,
          "eff": 0.153,
          "thrust_N": 118.369,
          "power_W": 2714.097,
          "torque_Nm": 3.703,
          "mach": 0.57
        },
        {
          "rpm": 7000.0,
          "V_mph": 11.77,
          "J": 0.0866,
          "Ct": 0.0954,
          "Cp": 0.0373,
          "eff": 0.2216,
          "thrust_N": 116.993,
          "power_W": 2777.229,
          "torque_Nm": 3.789,
          "mach": 0.57
        },
        {
          "rpm": 7000.0,
          "V_mph": 15.69,
          "J": 0.1155,
          "Ct": 0.0941,
          "Cp": 0.0381,
          "eff": 0.2853,
          "thrust_N": 115.437,
          "power_W": 2838.692,
          "torque_Nm": 3.873,
          "mach": 0.57
        },
        {
          "rpm": 7000.0,
          "V_mph": 19.62,
          "J": 0.1444,
          "Ct": 0.0927,
          "Cp": 0.0389,
          "eff": 0.3441,
          "thrust_N": 113.681,
          "power_W": 2897.172,
          "torque_Nm": 3.952,
          "mach": 0.57
        },
        {
          "rpm": 7000.0,
          "V_mph": 23.54,
          "J": 0.1732,
          "Ct": 0.0911,
          "Cp": 0.0396,
          "eff": 0.3983,
          "thrust_N": 111.706,
          "power_W": 2951.222,
          "torque_Nm": 4.026,
          "mach": 0.57
        },
        {
          "rpm": 7000.0,
          "V_mph": 27.46,
          "J": 0.2021,
          "Ct": 0.0893,
          "Cp": 0.0402,
          "eff": 0.4482,
          "thrust_N": 109.493,
          "power_W": 2999.286,
          "torque_Nm": 4.092,
          "mach": 0.57
        },
        {
          "rpm": 7000.0,
          "V_mph": 31.39,
          "J": 0.231,
          "Ct": 0.0872,
          "Cp": 0.0408,
          "eff": 0.494,
          "thrust_N": 107.026,
          "power_W": 3039.727,
          "torque_Nm": 4.147,
          "mach": 0.57
        },
        {
          "rpm": 7000.0,
          "V_mph": 35.31,
          "J": 0.2598,
          "Ct": 0.085,
          "Cp": 0.0412,
          "eff": 0.5361,
          "thrust_N": 104.288,
          "power_W": 3070.849,
          "torque_Nm": 4.189,
          "mach": 0.57
        },
        {
          "rpm": 7000.0,
          "V_mph": 39.23,
          "J": 0.2887,
          "Ct": 0.0826,
          "Cp": 0.0415,
          "eff": 0.5746,
          "thrust_N": 101.265,
          "power_W": 3090.947,
          "torque_Nm": 4.217,
          "mach": 0.57
        },
        {
          "rpm": 7000.0,
          "V_mph": 43.16,
          "J": 0.3176,
          "Ct": 0.0798,
          "Cp": 0.0416,
          "eff": 0.6099,
          "thrust_N": 97.945,
          "power_W": 3098.304,
          "torque_Nm": 4.227,
          "mach": 0.57
        },
        {
          "rpm": 7000.0,
          "V_mph": 47.08,
          "J": 0.3464,
          "Ct": 0.0769,
          "Cp": 0.0415,
          "eff": 0.6421,
          "thrust_N": 94.318,
          "power_W": 3091.254,
          "torque_Nm": 4.217,
          "mach": 0.57
        },
        {
          "rpm": 7000.0,
          "V_mph": 51.0,
          "J": 0.3753,
          "Ct": 0.0737,
          "Cp": 0.0412,
          "eff": 0.6716,
          "thrust_N": 90.378,
          "power_W": 3068.216,
          "torque_Nm": 4.186,
          "mach": 0.57
        },
        {
          "rpm": 7000.0,
          "V_mph": 54.93,
          "J": 0.4042,
          "Ct": 0.0702,
          "Cp": 0.0406,
          "eff": 0.6984,
          "thrust_N": 86.12,
          "power_W": 3027.698,
          "torque_Nm": 4.13,
          "mach": 0.57
        },
        {
          "rpm": 7000.0,
          "V_mph": 58.85,
          "J": 0.4331,
          "Ct": 0.0665,
          "Cp": 0.0398,
          "eff": 0.7227,
          "thrust_N": 81.539,
          "power_W": 2968.224,
          "torque_Nm": 4.049,
          "mach": 0.57
        },
        {
          "rpm": 7000.0,
          "V_mph": 62.77,
          "J": 0.4619,
          "Ct": 0.0625,
          "Cp": 0.0388,
          "eff": 0.7445,
          "thrust_N": 76.634,
          "power_W": 2888.451,
          "torque_Nm": 3.94,
          "mach": 0.58
        },
        {
          "rpm": 7000.0,
          "V_mph": 66.7,
          "J": 0.4908,
          "Ct": 0.0582,
          "Cp": 0.0374,
          "eff": 0.7639,
          "thrust_N": 71.434,
          "power_W": 2788.175,
          "torque_Nm": 3.804,
          "mach": 0.58
        },
        {
          "rpm": 7000.0,
          "V_mph": 70.62,
          "J": 0.5197,
          "Ct": 0.0538,
          "Cp": 0.0358,
          "eff": 0.7807,
          "thrust_N": 65.982,
          "power_W": 2668.053,
          "torque_Nm": 3.64,
          "mach": 0.58
        },
        {
          "rpm": 7000.0,
          "V_mph": 74.54,
          "J": 0.5485,
          "Ct": 0.0492,
          "Cp": 0.0339,
          "eff": 0.7948,
          "thrust_N": 60.319,
          "power_W": 2528.919,
          "torque_Nm": 3.45,
          "mach": 0.58
        },
        {
          "rpm": 7000.0,
          "V_mph": 78.47,
          "J": 0.5774,
          "Ct": 0.0444,
          "Cp": 0.0318,
          "eff": 0.8058,
          "thrust_N": 54.481,
          "power_W": 2371.628,
          "torque_Nm": 3.235,
          "mach": 0.58
        },
        {
          "rpm": 7000.0,
          "V_mph": 82.39,
          "J": 0.6063,
          "Ct": 0.0395,
          "Cp": 0.0295,
          "eff": 0.8131,
          "thrust_N": 48.503,
          "power_W": 2197.045,
          "torque_Nm": 2.997,
          "mach": 0.58
        },
        {
          "rpm": 7000.0,
          "V_mph": 86.31,
          "J": 0.6352,
          "Ct": 0.0346,
          "Cp": 0.0269,
          "eff": 0.8159,
          "thrust_N": 42.419,
          "power_W": 2006.09,
          "torque_Nm": 2.737,
          "mach": 0.58
        },
        {
          "rpm": 7000.0,
          "V_mph": 90.23,
          "J": 0.664,
          "Ct": 0.0296,
          "Cp": 0.0242,
          "eff": 0.8128,
          "thrust_N": 36.263,
          "power_W": 1799.776,
          "torque_Nm": 2.455,
          "mach": 0.58
        },
        {
          "rpm": 7000.0,
          "V_mph": 94.16,
          "J": 0.6929,
          "Ct": 0.0245,
          "Cp": 0.0212,
          "eff": 0.8014,
          "thrust_N": 30.07,
          "power_W": 1579.281,
          "torque_Nm": 2.154,
          "mach": 0.58
        },
        {
          "rpm": 7000.0,
          "V_mph": 98.08,
          "J": 0.7218,
          "Ct": 0.0195,
          "Cp": 0.0181,
          "eff": 0.7778,
          "thrust_N": 23.876,
          "power_W": 1345.991,
          "torque_Nm": 1.836,
          "mach": 0.58
        },
        {
          "rpm": 7000.0,
          "V_mph": 102.0,
          "J": 0.7506,
          "Ct": 0.0144,
          "Cp": 0.0148,
          "eff": 0.7336,
          "thrust_N": 17.722,
          "power_W": 1101.572,
          "torque_Nm": 1.503,
          "mach": 0.59
        },
        {
          "rpm": 7000.0,
          "V_mph": 105.93,
          "J": 0.7795,
          "Ct": 0.0095,
          "Cp": 0.0114,
          "eff": 0.6507,
          "thrust_N": 11.652,
          "power_W": 848.013,
          "torque_Nm": 1.157,
          "mach": 0.59
        },
        {
          "rpm": 7000.0,
          "V_mph": 109.85,
          "J": 0.8084,
          "Ct": 0.0047,
          "Cp": 0.0079,
          "eff": 0.4775,
          "thrust_N": 5.715,
          "power_W": 587.664,
          "torque_Nm": 0.802,
          "mach": 0.59
        },
        {
          "rpm": 7000.0,
          "V_mph": 113.77,
          "J": 0.8373,
          "Ct": 0.0,
          "Cp": 0.0043,
          "eff": -0.008,
          "thrust_N": -0.051,
          "power_W": 322.723,
          "torque_Nm": 0.44,
          "mach": 0.59
        },
        {
          "rpm": 8000.0,
          "V_mph": 0.0,
          "J": 0.0,
          "Ct": 0.0993,
          "Cp": 0.0351,
          "eff": 0.0,
          "thrust_N": 159.148,
          "power_W": 3905.862,
          "torque_Nm": 4.662,
          "mach": 0.65
        },
        {
          "rpm": 8000.0,
          "V_mph": 4.48,
          "J": 0.0288,
          "Ct": 0.0985,
          "Cp": 0.036,
          "eff": 0.079,
          "thrust_N": 157.834,
          "power_W": 4002.555,
          "torque_Nm": 4.778,
          "mach": 0.65
        },
        {
          "rpm": 8000.0,
          "V_mph": 8.96,
          "J": 0.0577,
          "Ct": 0.0976,
          "Cp": 0.0369,
          "eff": 0.1527,
          "thrust_N": 156.331,
          "power_W": 4100.418,
          "torque_Nm": 4.895,
          "mach": 0.65
        },
        {
          "rpm": 8000.0,
          "V_mph": 13.44,
          "J": 0.0865,
          "Ct": 0.0965,
          "Cp": 0.0377,
          "eff": 0.2213,
          "thrust_N": 154.618,
          "power_W": 4197.822,
          "torque_Nm": 5.011,
          "mach": 0.65
        },
        {
          "rpm": 8000.0,
          "V_mph": 17.92,
          "J": 0.1154,
          "Ct": 0.0953,
          "Cp": 0.0386,
          "eff": 0.2848,
          "thrust_N": 152.665,
          "power_W": 4292.951,
          "torque_Nm": 5.124,
          "mach": 0.65
        },
        {
          "rpm": 8000.0,
          "V_mph": 22.4,
          "J": 0.1442,
          "Ct": 0.0939,
          "Cp": 0.0394,
          "eff": 0.3436,
          "thrust_N": 150.448,
          "power_W": 4383.748,
          "torque_Nm": 5.233,
          "mach": 0.65
        },
        {
          "rpm": 8000.0,
          "V_mph": 26.88,
          "J": 0.1731,
          "Ct": 0.0923,
          "Cp": 0.0402,
          "eff": 0.3978,
          "thrust_N": 147.937,
          "power_W": 4467.936,
          "torque_Nm": 5.333,
          "mach": 0.65
        },
        {
          "rpm": 8000.0,
          "V_mph": 31.36,
          "J": 0.2019,
          "Ct": 0.0906,
          "Cp": 0.0408,
          "eff": 0.4477,
          "thrust_N": 145.108,
          "power_W": 4543.078,
          "torque_Nm": 5.423,
          "mach": 0.65
        },
        {
          "rpm": 8000.0,
          "V_mph": 35.84,
          "J": 0.2307,
          "Ct": 0.0886,
          "Cp": 0.0414,
          "eff": 0.4936,
          "thrust_N": 141.936,
          "power_W": 4606.619,
          "torque_Nm": 5.499,
          "mach": 0.65
        },
        {
          "rpm": 8000.0,
          "V_mph": 40.31,
          "J": 0.2596,
          "Ct": 0.0864,
          "Cp": 0.0419,
          "eff": 0.5357,
          "thrust_N": 138.399,
          "power_W": 4655.915,
          "torque_Nm": 5.558,
          "mach": 0.65
        },
        {
          "rpm": 8000.0,
          "V_mph": 44.79,
          "J": 0.2884,
          "Ct": 0.0839,
          "Cp": 0.0421,
          "eff": 0.5744,
          "thrust_N": 134.477,
          "power_W": 4688.316,
          "torque_Nm": 5.596,
          "mach": 0.65
        },
        {
          "rpm": 8000.0,
          "V_mph": 49.27,
          "J": 0.3173,
          "Ct": 0.0812,
          "Cp": 0.0423,
          "eff": 0.6098,
          "thrust_N": 130.152,
          "power_W": 4701.166,
          "torque_Nm": 5.612,
          "mach": 0.65
        },
        {
          "rpm": 8000.0,
          "V_mph": 53.75,
          "J": 0.3461,
          "Ct": 0.0783,
          "Cp": 0.0422,
          "eff": 0.6423,
          "thrust_N": 125.411,
          "power_W": 4691.886,
          "torque_Nm": 5.601,
          "mach": 0.65
        },
        {
          "rpm": 8000.0,
          "V_mph": 58.23,
          "J": 0.375,
          "Ct": 0.075,
          "Cp": 0.0419,
          "eff": 0.672,
          "thrust_N": 120.245,
          "power_W": 4658.028,
          "torque_Nm": 5.56,
          "mach": 0.66
        },
        {
          "rpm": 8000.0,
          "V_mph": 62.71,
          "J": 0.4038,
          "Ct": 0.0716,
          "Cp": 0.0413,
          "eff": 0.6991,
          "thrust_N": 114.647,
          "power_W": 4597.31,
          "torque_Nm": 5.488,
          "mach": 0.66
        },
        {
          "rpm": 8000.0,
          "V_mph": 67.19,
          "J": 0.4326,
          "Ct": 0.0678,
          "Cp": 0.0405,
          "eff": 0.7238,
          "thrust_N": 108.61,
          "power_W": 4507.488,
          "torque_Nm": 5.38,
          "mach": 0.66
        },
        {
          "rpm": 8000.0,
          "V_mph": 71.67,
          "J": 0.4615,
          "Ct": 0.0637,
          "Cp": 0.0394,
          "eff": 0.746,
          "thrust_N": 102.134,
          "power_W": 4386.476,
          "torque_Nm": 5.236,
          "mach": 0.66
        },
        {
          "rpm": 8000.0,
          "V_mph": 76.15,
          "J": 0.4903,
          "Ct": 0.0595,
          "Cp": 0.0381,
          "eff": 0.7659,
          "thrust_N": 95.254,
          "power_W": 4233.822,
          "torque_Nm": 5.054,
          "mach": 0.66
        },
        {
          "rpm": 8000.0,
          "V_mph": 80.63,
          "J": 0.5192,
          "Ct": 0.0549,
          "Cp": 0.0364,
          "eff": 0.7833,
          "thrust_N": 88.026,
          "power_W": 4050.483,
          "torque_Nm": 4.835,
          "mach": 0.66
        },
        {
          "rpm": 8000.0,
          "V_mph": 85.11,
          "J": 0.548,
          "Ct": 0.0502,
          "Cp": 0.0345,
          "eff": 0.7981,
          "thrust_N": 80.507,
          "power_W": 3837.756,
          "torque_Nm": 4.581,
          "mach": 0.66
        },
        {
          "rpm": 8000.0,
          "V_mph": 89.59,
          "J": 0.5769,
          "Ct": 0.0454,
          "Cp": 0.0323,
          "eff": 0.81,
          "thrust_N": 72.745,
          "power_W": 3596.97,
          "torque_Nm": 4.294,
          "mach": 0.66
        },
        {
          "rpm": 8000.0,
          "V_mph": 94.07,
          "J": 0.6057,
          "Ct": 0.0404,
          "Cp": 0.0299,
          "eff": 0.8183,
          "thrust_N": 64.788,
          "power_W": 3329.463,
          "torque_Nm": 3.974,
          "mach": 0.66
        },
        {
          "rpm": 8000.0,
          "V_mph": 98.55,
          "J": 0.6345,
          "Ct": 0.0354,
          "Cp": 0.0273,
          "eff": 0.8223,
          "thrust_N": 56.682,
          "power_W": 3036.65,
          "torque_Nm": 3.625,
          "mach": 0.66
        },
        {
          "rpm": 8000.0,
          "V_mph": 103.03,
          "J": 0.6634,
          "Ct": 0.0303,
          "Cp": 0.0245,
          "eff": 0.8207,
          "thrust_N": 48.472,
          "power_W": 2720.104,
          "torque_Nm": 3.247,
          "mach": 0.66
        },
        {
          "rpm": 8000.0,
          "V_mph": 107.51,
          "J": 0.6922,
          "Ct": 0.0251,
          "Cp": 0.0214,
          "eff": 0.8113,
          "thrust_N": 40.205,
          "power_W": 2381.635,
          "torque_Nm": 2.843,
          "mach": 0.67
        },
        {
          "rpm": 8000.0,
          "V_mph": 111.98,
          "J": 0.7211,
          "Ct": 0.0199,
          "Cp": 0.0182,
          "eff": 0.79,
          "thrust_N": 31.932,
          "power_W": 2023.386,
          "torque_Nm": 2.415,
          "mach": 0.67
        },
        {
          "rpm": 8000.0,
          "V_mph": 116.46,
          "J": 0.7499,
          "Ct": 0.0148,
          "Cp": 0.0148,
          "eff": 0.7489,
          "thrust_N": 23.706,
          "power_W": 1647.938,
          "torque_Nm": 1.967,
          "mach": 0.67
        },
        {
          "rpm": 8000.0,
          "V_mph": 120.94,
          "J": 0.7788,
          "Ct": 0.0097,
          "Cp": 0.0113,
          "eff": 0.6697,
          "thrust_N": 15.588,
          "power_W": 1258.431,
          "torque_Nm": 1.502,
          "mach": 0.67
        },
        {
          "rpm": 8000.0,
          "V_mph": 125.42,
          "J": 0.8076,
          "Ct": 0.0048,
          "Cp": 0.0077,
          "eff": 0.4991,
          "thrust_N": 7.644,
          "power_W": 858.616,
          "torque_Nm": 1.025,
          "mach": 0.67
        },
        {
          "rpm": 8000.0,
          "V_mph": 129.9,
          "J": 0.8364,
          "Ct": 0.0,
          "Cp": 0.0041,
          "eff": -0.0093,
          "thrust_N": -0.072,
          "power_W": 452.044,
          "torque_Nm": 0.54,
          "mach": 0.67
        },
        {
          "rpm": 9000.0,
          "V_mph": 0.0,
          "J": 0.0,
          "Ct": 0.1004,
          "Cp": 0.0362,
          "eff": 0.0,
          "thrust_N": 203.673,
          "power_W": 5730.89,
          "torque_Nm": 6.081,
          "mach": 0.73
        },
        {
          "rpm": 9000.0,
          "V_mph": 5.03,
          "J": 0.0288,
          "Ct": 0.0997,
          "Cp": 0.037,
          "eff": 0.0775,
          "thrust_N": 202.149,
          "power_W": 5864.418,
          "torque_Nm": 6.222,
          "mach": 0.73
        },
        {
          "rpm": 9000.0,
          "V_mph": 10.06,
          "J": 0.0576,
          "Ct": 0.0988,
          "Cp": 0.0379,
          "eff": 0.1503,
          "thrust_N": 200.393,
          "power_W": 5999.943,
          "torque_Nm": 6.366,
          "mach": 0.73
        },
        {
          "rpm": 9000.0,
          "V_mph": 15.1,
          "J": 0.0864,
          "Ct": 0.0978,
          "Cp": 0.0387,
          "eff": 0.2182,
          "thrust_N": 198.372,
          "power_W": 6135.26,
          "torque_Nm": 6.51,
          "mach": 0.73
        },
        {
          "rpm": 9000.0,
          "V_mph": 20.13,
          "J": 0.1152,
          "Ct": 0.0967,
          "Cp": 0.0396,
          "eff": 0.2814,
          "thrust_N": 196.047,
          "power_W": 6267.871,
          "torque_Nm": 6.65,
          "mach": 0.73
        },
        {
          "rpm": 9000.0,
          "V_mph": 25.16,
          "J": 0.144,
          "Ct": 0.0954,
          "Cp": 0.0404,
          "eff": 0.3401,
          "thrust_N": 193.381,
          "power_W": 6394.949,
          "torque_Nm": 6.785,
          "mach": 0.73
        },
        {
          "rpm": 9000.0,
          "V_mph": 30.19,
          "J": 0.1728,
          "Ct": 0.0939,
          "Cp": 0.0411,
          "eff": 0.3944,
          "thrust_N": 190.337,
          "power_W": 6513.311,
          "torque_Nm": 6.911,
          "mach": 0.73
        },
        {
          "rpm": 9000.0,
          "V_mph": 35.22,
          "J": 0.2016,
          "Ct": 0.0922,
          "Cp": 0.0418,
          "eff": 0.4445,
          "thrust_N": 186.876,
          "power_W": 6619.518,
          "torque_Nm": 7.024,
          "mach": 0.73
        },
        {
          "rpm": 9000.0,
          "V_mph": 40.26,
          "J": 0.2304,
          "Ct": 0.0902,
          "Cp": 0.0424,
          "eff": 0.4907,
          "thrust_N": 182.965,
          "power_W": 6709.882,
          "torque_Nm": 7.119,
          "mach": 0.73
        },
        {
          "rpm": 9000.0,
          "V_mph": 45.29,
          "J": 0.2592,
          "Ct": 0.0881,
          "Cp": 0.0428,
          "eff": 0.5332,
          "thrust_N": 178.571,
          "power_W": 6780.57,
          "torque_Nm": 7.194,
          "mach": 0.73
        },
        {
          "rpm": 9000.0,
          "V_mph": 50.32,
          "J": 0.288,
          "Ct": 0.0856,
          "Cp": 0.0431,
          "eff": 0.5722,
          "thrust_N": 173.667,
          "power_W": 6827.605,
          "torque_Nm": 7.244,
          "mach": 0.73
        },
        {
          "rpm": 9000.0,
          "V_mph": 55.35,
          "J": 0.3168,
          "Ct": 0.083,
          "Cp": 0.0432,
          "eff": 0.608,
          "thrust_N": 168.23,
          "power_W": 6846.997,
          "torque_Nm": 7.265,
          "mach": 0.74
        },
        {
          "rpm": 9000.0,
          "V_mph": 60.38,
          "J": 0.3456,
          "Ct": 0.08,
          "Cp": 0.0432,
          "eff": 0.6408,
          "thrust_N": 162.241,
          "power_W": 6834.763,
          "torque_Nm": 7.252,
          "mach": 0.74
        },
        {
          "rpm": 9000.0,
          "V_mph": 65.42,
          "J": 0.3744,
          "Ct": 0.0768,
          "Cp": 0.0429,
          "eff": 0.6708,
          "thrust_N": 155.685,
          "power_W": 6787.023,
          "torque_Nm": 7.201,
          "mach": 0.74
        },
        {
          "rpm": 9000.0,
          "V_mph": 70.45,
          "J": 0.4032,
          "Ct": 0.0733,
          "Cp": 0.0423,
          "eff": 0.6983,
          "thrust_N": 148.556,
          "power_W": 6700.133,
          "torque_Nm": 7.109,
          "mach": 0.74
        },
        {
          "rpm": 9000.0,
          "V_mph": 75.48,
          "J": 0.432,
          "Ct": 0.0695,
          "Cp": 0.0415,
          "eff": 0.7233,
          "thrust_N": 140.845,
          "power_W": 6570.561,
          "torque_Nm": 6.972,
          "mach": 0.74
        },
        {
          "rpm": 9000.0,
          "V_mph": 80.51,
          "J": 0.4608,
          "Ct": 0.0654,
          "Cp": 0.0404,
          "eff": 0.746,
          "thrust_N": 132.549,
          "power_W": 6395.027,
          "torque_Nm": 6.785,
          "mach": 0.74
        },
        {
          "rpm": 9000.0,
          "V_mph": 85.54,
          "J": 0.4896,
          "Ct": 0.061,
          "Cp": 0.039,
          "eff": 0.7664,
          "thrust_N": 123.71,
          "power_W": 6172.596,
          "torque_Nm": 6.549,
          "mach": 0.74
        },
        {
          "rpm": 9000.0,
          "V_mph": 90.58,
          "J": 0.5184,
          "Ct": 0.0564,
          "Cp": 0.0373,
          "eff": 0.7845,
          "thrust_N": 114.402,
          "power_W": 5904.605,
          "torque_Nm": 6.265,
          "mach": 0.74
        },
        {
          "rpm": 9000.0,
          "V_mph": 95.61,
          "J": 0.5472,
          "Ct": 0.0516,
          "Cp": 0.0353,
          "eff": 0.8001,
          "thrust_N": 104.697,
          "power_W": 5592.986,
          "torque_Nm": 5.934,
          "mach": 0.74
        },
        {
          "rpm": 9000.0,
          "V_mph": 100.64,
          "J": 0.576,
          "Ct": 0.0467,
          "Cp": 0.0331,
          "eff": 0.8128,
          "thrust_N": 94.661,
          "power_W": 5239.775,
          "torque_Nm": 5.56,
          "mach": 0.74
        },
        {
          "rpm": 9000.0,
          "V_mph": 105.67,
          "J": 0.6048,
          "Ct": 0.0416,
          "Cp": 0.0306,
          "eff": 0.8222,
          "thrust_N": 84.357,
          "power_W": 4847.087,
          "torque_Nm": 5.143,
          "mach": 0.75
        },
        {
          "rpm": 9000.0,
          "V_mph": 110.71,
          "J": 0.6336,
          "Ct": 0.0364,
          "Cp": 0.0279,
          "eff": 0.8273,
          "thrust_N": 73.845,
          "power_W": 4417.201,
          "torque_Nm": 4.687,
          "mach": 0.75
        },
        {
          "rpm": 9000.0,
          "V_mph": 115.74,
          "J": 0.6624,
          "Ct": 0.0312,
          "Cp": 0.025,
          "eff": 0.827,
          "thrust_N": 63.183,
          "power_W": 3952.681,
          "torque_Nm": 4.194,
          "mach": 0.75
        },
        {
          "rpm": 9000.0,
          "V_mph": 120.77,
          "J": 0.6912,
          "Ct": 0.0259,
          "Cp": 0.0218,
          "eff": 0.819,
          "thrust_N": 52.435,
          "power_W": 3456.583,
          "torque_Nm": 3.668,
          "mach": 0.75
        },
        {
          "rpm": 9000.0,
          "V_mph": 125.8,
          "J": 0.72,
          "Ct": 0.0205,
          "Cp": 0.0185,
          "eff": 0.799,
          "thrust_N": 41.664,
          "power_W": 2932.606,
          "torque_Nm": 3.112,
          "mach": 0.75
        },
        {
          "rpm": 9000.0,
          "V_mph": 130.83,
          "J": 0.7488,
          "Ct": 0.0153,
          "Cp": 0.0151,
          "eff": 0.7587,
          "thrust_N": 30.942,
          "power_W": 2385.312,
          "torque_Nm": 2.531,
          "mach": 0.75
        },
        {
          "rpm": 9000.0,
          "V_mph": 135.87,
          "J": 0.7776,
          "Ct": 0.01,
          "Cp": 0.0115,
          "eff": 0.679,
          "thrust_N": 20.348,
          "power_W": 1820.286,
          "torque_Nm": 1.931,
          "mach": 0.75
        },
        {
          "rpm": 9000.0,
          "V_mph": 140.9,
          "J": 0.8064,
          "Ct": 0.0049,
          "Cp": 0.0079,
          "eff": 0.5047,
          "thrust_N": 9.969,
          "power_W": 1244.215,
          "torque_Nm": 1.32,
          "mach": 0.76
        },
        {
          "rpm": 9000.0,
          "V_mph": 145.93,
          "J": 0.8352,
          "Ct": -0.0001,
          "Cp": 0.0042,
          "eff": -0.0121,
          "thrust_N": -0.123,
          "power_W": 663.57,
          "torque_Nm": 0.704,
          "mach": 0.76
        },
        {
          "rpm": 10000.0,
          "V_mph": 0.0,
          "J": 0.0,
          "Ct": 0.1016,
          "Cp": 0.0399,
          "eff": 0.0,
          "thrust_N": 254.361,
          "power_W": 8662.162,
          "torque_Nm": 8.272,
          "mach": 0.81
        },
        {
          "rpm": 10000.0,
          "V_mph": 5.58,
          "J": 0.0287,
          "Ct": 0.1009,
          "Cp": 0.0406,
          "eff": 0.0714,
          "thrust_N": 252.708,
          "power_W": 8825.055,
          "torque_Nm": 8.427,
          "mach": 0.81
        },
        {
          "rpm": 10000.0,
          "V_mph": 11.16,
          "J": 0.0575,
          "Ct": 0.1002,
          "Cp": 0.0414,
          "eff": 0.1391,
          "thrust_N": 250.784,
          "power_W": 8988.668,
          "torque_Nm": 8.584,
          "mach": 0.81
        },
        {
          "rpm": 10000.0,
          "V_mph": 16.73,
          "J": 0.0862,
          "Ct": 0.0993,
          "Cp": 0.0421,
          "eff": 0.2032,
          "thrust_N": 248.542,
          "power_W": 9149.75,
          "torque_Nm": 8.737,
          "mach": 0.81
        },
        {
          "rpm": 10000.0,
          "V_mph": 22.31,
          "J": 0.1149,
          "Ct": 0.0982,
          "Cp": 0.0428,
          "eff": 0.2636,
          "thrust_N": 245.934,
          "power_W": 9304.763,
          "torque_Nm": 8.885,
          "mach": 0.81
        },
        {
          "rpm": 10000.0,
          "V_mph": 27.89,
          "J": 0.1437,
          "Ct": 0.097,
          "Cp": 0.0435,
          "eff": 0.3205,
          "thrust_N": 242.905,
          "power_W": 9449.706,
          "torque_Nm": 9.024,
          "mach": 0.81
        },
        {
          "rpm": 10000.0,
          "V_mph": 33.47,
          "J": 0.1724,
          "Ct": 0.0956,
          "Cp": 0.0441,
          "eff": 0.3739,
          "thrust_N": 239.402,
          "power_W": 9580.31,
          "torque_Nm": 9.149,
          "mach": 0.81
        },
        {
          "rpm": 10000.0,
          "V_mph": 39.04,
          "J": 0.2011,
          "Ct": 0.094,
          "Cp": 0.0446,
          "eff": 0.4239,
          "thrust_N": 235.373,
          "power_W": 9692.074,
          "torque_Nm": 9.255,
          "mach": 0.81
        },
        {
          "rpm": 10000.0,
          "V_mph": 44.62,
          "J": 0.2299,
          "Ct": 0.0922,
          "Cp": 0.045,
          "eff": 0.4707,
          "thrust_N": 230.767,
          "power_W": 9780.418,
          "torque_Nm": 9.34,
          "mach": 0.82
        },
        {
          "rpm": 10000.0,
          "V_mph": 50.2,
          "J": 0.2586,
          "Ct": 0.0901,
          "Cp": 0.0453,
          "eff": 0.5143,
          "thrust_N": 225.537,
          "power_W": 9840.728,
          "torque_Nm": 9.397,
          "mach": 0.82
        },
        {
          "rpm": 10000.0,
          "V_mph": 55.78,
          "J": 0.2873,
          "Ct": 0.0877,
          "Cp": 0.0454,
          "eff": 0.555,
          "thrust_N": 219.645,
          "power_W": 9868.368,
          "torque_Nm": 9.424,
          "mach": 0.82
        },
        {
          "rpm": 10000.0,
          "V_mph": 61.36,
          "J": 0.3161,
          "Ct": 0.0851,
          "Cp": 0.0454,
          "eff": 0.5928,
          "thrust_N": 213.055,
          "power_W": 9858.733,
          "torque_Nm": 9.414,
          "mach": 0.82
        },
        {
          "rpm": 10000.0,
          "V_mph": 66.93,
          "J": 0.3448,
          "Ct": 0.0822,
          "Cp": 0.0451,
          "eff": 0.6277,
          "thrust_N": 205.741,
          "power_W": 9807.267,
          "torque_Nm": 9.365,
          "mach": 0.82
        },
        {
          "rpm": 10000.0,
          "V_mph": 72.51,
          "J": 0.3735,
          "Ct": 0.079,
          "Cp": 0.0447,
          "eff": 0.66,
          "thrust_N": 197.684,
          "power_W": 9709.451,
          "torque_Nm": 9.272,
          "mach": 0.82
        },
        {
          "rpm": 10000.0,
          "V_mph": 78.09,
          "J": 0.4023,
          "Ct": 0.0754,
          "Cp": 0.044,
          "eff": 0.6896,
          "thrust_N": 188.87,
          "power_W": 9560.855,
          "torque_Nm": 9.13,
          "mach": 0.82
        },
        {
          "rpm": 10000.0,
          "V_mph": 83.67,
          "J": 0.431,
          "Ct": 0.0716,
          "Cp": 0.0431,
          "eff": 0.7167,
          "thrust_N": 179.292,
          "power_W": 9356.977,
          "torque_Nm": 8.935,
          "mach": 0.82
        },
        {
          "rpm": 10000.0,
          "V_mph": 89.24,
          "J": 0.4597,
          "Ct": 0.0675,
          "Cp": 0.0419,
          "eff": 0.7412,
          "thrust_N": 168.943,
          "power_W": 9093.039,
          "torque_Nm": 8.683,
          "mach": 0.82
        },
        {
          "rpm": 10000.0,
          "V_mph": 94.82,
          "J": 0.4885,
          "Ct": 0.0631,
          "Cp": 0.0404,
          "eff": 0.7633,
          "thrust_N": 157.867,
          "power_W": 8766.952,
          "torque_Nm": 8.372,
          "mach": 0.82
        },
        {
          "rpm": 10000.0,
          "V_mph": 100.4,
          "J": 0.5172,
          "Ct": 0.0584,
          "Cp": 0.0386,
          "eff": 0.7827,
          "thrust_N": 146.157,
          "power_W": 8381.583,
          "torque_Nm": 8.004,
          "mach": 0.82
        },
        {
          "rpm": 10000.0,
          "V_mph": 105.98,
          "J": 0.5459,
          "Ct": 0.0535,
          "Cp": 0.0365,
          "eff": 0.7991,
          "thrust_N": 133.908,
          "power_W": 7938.703,
          "torque_Nm": 7.581,
          "mach": 0.83
        },
        {
          "rpm": 10000.0,
          "V_mph": 111.56,
          "J": 0.5746,
          "Ct": 0.0484,
          "Cp": 0.0343,
          "eff": 0.8123,
          "thrust_N": 121.208,
          "power_W": 7441.286,
          "torque_Nm": 7.106,
          "mach": 0.83
        },
        {
          "rpm": 10000.0,
          "V_mph": 117.13,
          "J": 0.6034,
          "Ct": 0.0432,
          "Cp": 0.0317,
          "eff": 0.8216,
          "thrust_N": 108.137,
          "power_W": 6892.061,
          "torque_Nm": 6.581,
          "mach": 0.83
        },
        {
          "rpm": 10000.0,
          "V_mph": 122.71,
          "J": 0.6321,
          "Ct": 0.0379,
          "Cp": 0.029,
          "eff": 0.826,
          "thrust_N": 94.774,
          "power_W": 6294.112,
          "torque_Nm": 6.01,
          "mach": 0.83
        },
        {
          "rpm": 10000.0,
          "V_mph": 128.29,
          "J": 0.6608,
          "Ct": 0.0324,
          "Cp": 0.026,
          "eff": 0.8238,
          "thrust_N": 81.195,
          "power_W": 5652.558,
          "torque_Nm": 5.398,
          "mach": 0.83
        },
        {
          "rpm": 10000.0,
          "V_mph": 133.87,
          "J": 0.6896,
          "Ct": 0.027,
          "Cp": 0.0229,
          "eff": 0.8119,
          "thrust_N": 67.479,
          "power_W": 4973.632,
          "torque_Nm": 4.749,
          "mach": 0.83
        },
        {
          "rpm": 10000.0,
          "V_mph": 139.44,
          "J": 0.7183,
          "Ct": 0.0215,
          "Cp": 0.0196,
          "eff": 0.785,
          "thrust_N": 53.708,
          "power_W": 4264.939,
          "torque_Nm": 4.073,
          "mach": 0.83
        },
        {
          "rpm": 10000.0,
          "V_mph": 145.02,
          "J": 0.747,
          "Ct": 0.016,
          "Cp": 0.0163,
          "eff": 0.733,
          "thrust_N": 39.972,
          "power_W": 3535.388,
          "torque_Nm": 3.376,
          "mach": 0.84
        },
        {
          "rpm": 10000.0,
          "V_mph": 150.6,
          "J": 0.7758,
          "Ct": 0.0105,
          "Cp": 0.0129,
          "eff": 0.6352,
          "thrust_N": 26.373,
          "power_W": 2795.278,
          "torque_Nm": 2.669,
          "mach": 0.84
        },
        {
          "rpm": 10000.0,
          "V_mph": 156.18,
          "J": 0.8045,
          "Ct": 0.0052,
          "Cp": 0.0095,
          "eff": 0.4422,
          "thrust_N": 13.022,
          "power_W": 2056.154,
          "torque_Nm": 1.963,
          "mach": 0.84
        },
        {
          "rpm": 10000.0,
          "V_mph": 161.76,
          "J": 0.8332,
          "Ct": 0.0,
          "Cp": 0.0061,
          "eff": 0.0018,
          "thrust_N": 0.033,
          "power_W": 1329.005,
          "torque_Nm": 1.269,
          "mach": 0.84
        },
        {
          "rpm": 11000.0,
          "V_mph": 0.0,
          "J": 0.0,
          "Ct": 0.1021,
          "Cp": 0.0475,
          "eff": 0.0,
          "thrust_N": 309.143,
          "power_W": 13729.15,
          "torque_Nm": 11.919,
          "mach": 0.89
        },
        {
          "rpm": 11000.0,
          "V_mph": 6.16,
          "J": 0.0289,
          "Ct": 0.1015,
          "Cp": 0.0482,
          "eff": 0.0608,
          "thrust_N": 307.537,
          "power_W": 13941.109,
          "torque_Nm": 12.103,
          "mach": 0.89
        },
        {
          "rpm": 11000.0,
          "V_mph": 12.33,
          "J": 0.0577,
          "Ct": 0.1009,
          "Cp": 0.0489,
          "eff": 0.119,
          "thrust_N": 305.635,
          "power_W": 14149.326,
          "torque_Nm": 12.283,
          "mach": 0.89
        },
        {
          "rpm": 11000.0,
          "V_mph": 18.49,
          "J": 0.0866,
          "Ct": 0.1002,
          "Cp": 0.0496,
          "eff": 0.1748,
          "thrust_N": 303.377,
          "power_W": 14347.807,
          "torque_Nm": 12.456,
          "mach": 0.89
        },
        {
          "rpm": 11000.0,
          "V_mph": 24.65,
          "J": 0.1154,
          "Ct": 0.0993,
          "Cp": 0.0502,
          "eff": 0.2281,
          "thrust_N": 300.696,
          "power_W": 14529.933,
          "torque_Nm": 12.614,
          "mach": 0.9
        },
        {
          "rpm": 11000.0,
          "V_mph": 30.81,
          "J": 0.1443,
          "Ct": 0.0982,
          "Cp": 0.0508,
          "eff": 0.279,
          "thrust_N": 297.518,
          "power_W": 14688.546,
          "torque_Nm": 12.751,
          "mach": 0.9
        },
        {
          "rpm": 11000.0,
          "V_mph": 36.98,
          "J": 0.1732,
          "Ct": 0.097,
          "Cp": 0.0512,
          "eff": 0.3277,
          "thrust_N": 293.766,
          "power_W": 14816.195,
          "torque_Nm": 12.862,
          "mach": 0.9
        },
        {
          "rpm": 11000.0,
          "V_mph": 43.14,
          "J": 0.202,
          "Ct": 0.0955,
          "Cp": 0.0515,
          "eff": 0.3744,
          "thrust_N": 289.362,
          "power_W": 14905.552,
          "torque_Nm": 12.94,
          "mach": 0.9
        },
        {
          "rpm": 11000.0,
          "V_mph": 49.3,
          "J": 0.2309,
          "Ct": 0.0938,
          "Cp": 0.0517,
          "eff": 0.419,
          "thrust_N": 284.232,
          "power_W": 14949.74,
          "torque_Nm": 12.978,
          "mach": 0.9
        },
        {
          "rpm": 11000.0,
          "V_mph": 55.46,
          "J": 0.2597,
          "Ct": 0.0919,
          "Cp": 0.0517,
          "eff": 0.4618,
          "thrust_N": 278.306,
          "power_W": 14942.613,
          "torque_Nm": 12.972,
          "mach": 0.9
        },
        {
          "rpm": 11000.0,
          "V_mph": 61.63,
          "J": 0.2886,
          "Ct": 0.0896,
          "Cp": 0.0515,
          "eff": 0.5027,
          "thrust_N": 271.521,
          "power_W": 14878.859,
          "torque_Nm": 12.917,
          "mach": 0.9
        },
        {
          "rpm": 11000.0,
          "V_mph": 67.79,
          "J": 0.3175,
          "Ct": 0.0871,
          "Cp": 0.051,
          "eff": 0.5419,
          "thrust_N": 263.825,
          "power_W": 14753.984,
          "torque_Nm": 12.808,
          "mach": 0.9
        },
        {
          "rpm": 11000.0,
          "V_mph": 73.95,
          "J": 0.3463,
          "Ct": 0.0842,
          "Cp": 0.0504,
          "eff": 0.5792,
          "thrust_N": 255.174,
          "power_W": 14564.146,
          "torque_Nm": 12.643,
          "mach": 0.9
        },
        {
          "rpm": 11000.0,
          "V_mph": 80.11,
          "J": 0.3752,
          "Ct": 0.0811,
          "Cp": 0.0495,
          "eff": 0.6147,
          "thrust_N": 245.537,
          "power_W": 14305.958,
          "torque_Nm": 12.419,
          "mach": 0.9
        },
        {
          "rpm": 11000.0,
          "V_mph": 86.28,
          "J": 0.404,
          "Ct": 0.0775,
          "Cp": 0.0483,
          "eff": 0.6482,
          "thrust_N": 234.895,
          "power_W": 13976.544,
          "torque_Nm": 12.133,
          "mach": 0.9
        },
        {
          "rpm": 11000.0,
          "V_mph": 92.44,
          "J": 0.4329,
          "Ct": 0.0737,
          "Cp": 0.0469,
          "eff": 0.6797,
          "thrust_N": 223.236,
          "power_W": 13572.973,
          "torque_Nm": 11.783,
          "mach": 0.9
        },
        {
          "rpm": 11000.0,
          "V_mph": 98.6,
          "J": 0.4617,
          "Ct": 0.0695,
          "Cp": 0.0453,
          "eff": 0.7089,
          "thrust_N": 210.549,
          "power_W": 13091.507,
          "torque_Nm": 11.365,
          "mach": 0.9
        },
        {
          "rpm": 11000.0,
          "V_mph": 104.76,
          "J": 0.4906,
          "Ct": 0.065,
          "Cp": 0.0433,
          "eff": 0.7358,
          "thrust_N": 196.897,
          "power_W": 12532.281,
          "torque_Nm": 10.879,
          "mach": 0.91
        },
        {
          "rpm": 11000.0,
          "V_mph": 110.93,
          "J": 0.5195,
          "Ct": 0.0602,
          "Cp": 0.0412,
          "eff": 0.7601,
          "thrust_N": 182.4,
          "power_W": 11900.479,
          "torque_Nm": 10.331,
          "mach": 0.91
        },
        {
          "rpm": 11000.0,
          "V_mph": 117.09,
          "J": 0.5483,
          "Ct": 0.0552,
          "Cp": 0.0388,
          "eff": 0.7803,
          "thrust_N": 167.174,
          "power_W": 11214.823,
          "torque_Nm": 9.736,
          "mach": 0.91
        },
        {
          "rpm": 11000.0,
          "V_mph": 123.25,
          "J": 0.5772,
          "Ct": 0.05,
          "Cp": 0.0362,
          "eff": 0.7959,
          "thrust_N": 151.336,
          "power_W": 10476.826,
          "torque_Nm": 9.095,
          "mach": 0.91
        },
        {
          "rpm": 11000.0,
          "V_mph": 129.42,
          "J": 0.606,
          "Ct": 0.0446,
          "Cp": 0.0335,
          "eff": 0.8051,
          "thrust_N": 134.987,
          "power_W": 9700.026,
          "torque_Nm": 8.421,
          "mach": 0.91
        },
        {
          "rpm": 11000.0,
          "V_mph": 135.58,
          "J": 0.6349,
          "Ct": 0.039,
          "Cp": 0.0308,
          "eff": 0.8037,
          "thrust_N": 118.212,
          "power_W": 8914.658,
          "torque_Nm": 7.739,
          "mach": 0.91
        },
        {
          "rpm": 11000.0,
          "V_mph": 141.74,
          "J": 0.6638,
          "Ct": 0.0334,
          "Cp": 0.028,
          "eff": 0.7907,
          "thrust_N": 101.138,
          "power_W": 8104.883,
          "torque_Nm": 7.036,
          "mach": 0.91
        },
        {
          "rpm": 11000.0,
          "V_mph": 147.9,
          "J": 0.6926,
          "Ct": 0.0277,
          "Cp": 0.0251,
          "eff": 0.7631,
          "thrust_N": 83.889,
          "power_W": 7268.205,
          "torque_Nm": 6.31,
          "mach": 0.92
        },
        {
          "rpm": 11000.0,
          "V_mph": 154.07,
          "J": 0.7215,
          "Ct": 0.022,
          "Cp": 0.0222,
          "eff": 0.7146,
          "thrust_N": 66.593,
          "power_W": 6418.634,
          "torque_Nm": 5.572,
          "mach": 0.92
        },
        {
          "rpm": 11000.0,
          "V_mph": 160.23,
          "J": 0.7503,
          "Ct": 0.0163,
          "Cp": 0.0193,
          "eff": 0.635,
          "thrust_N": 49.386,
          "power_W": 5571.177,
          "torque_Nm": 4.836,
          "mach": 0.92
        },
        {
          "rpm": 11000.0,
          "V_mph": 166.39,
          "J": 0.7792,
          "Ct": 0.0107,
          "Cp": 0.0164,
          "eff": 0.5087,
          "thrust_N": 32.422,
          "power_W": 4740.837,
          "torque_Nm": 4.116,
          "mach": 0.92
        },
        {
          "rpm": 11000.0,
          "V_mph": 172.55,
          "J": 0.8081,
          "Ct": 0.0052,
          "Cp": 0.0136,
          "eff": 0.3107,
          "thrust_N": 15.877,
          "power_W": 3941.999,
          "torque_Nm": 3.422,
          "mach": 0.92
        },
        {
          "rpm": 11000.0,
          "V_mph": 178.72,
          "J": 0.8369,
          "Ct": 0.0,
          "Cp": 0.011,
          "eff": -0.0027,
          "thrust_N": -0.109,
          "power_W": 3180.82,
          "torque_Nm": 2.761,
          "mach": 0.93
        }
      ]
    },
    "empirical": null
  }
}