{
  "meta": {
    "name": "ancf_13x65",
    "diameter_in": 13.0,
    "pitch_in": 65.0,
    "blades": 2,
    "type": null,
    "apc_name": null,
    "uiuc_name": "ancf_13x65",
    "has_simulated": false,
    "has_empirical": true
  },
  "sources": {
    "simulated": null,
    "empirical": {
      "rpm_min": 1013,
      "rpm_max": 7453,
      "n_points": 190,
      "volumes": [
        "volume-3"
      ],
      "geometry": null,
      "sweep": [
        {
          "kind": "dynamic",
          "rpm": 3035.0,
          "J": 0.138,
          "CT": 0.0786,
          "CP": 0.0322,
          "eta": 0.337
        },
        {
          "kind": "dynamic",
          "rpm": 3035.0,
          "J": 0.1751,
          "CT": 0.0752,
          "CP": 0.032,
          "eta": 0.411
        },
        {
          "kind": "dynamic",
          "rpm": 3035.0,
          "J": 0.2115,
          "CT": 0.0723,
          "CP": 0.032,
          "eta": 0.4776
        },
        {
          "kind": "dynamic",
          "rpm": 3035.0,
          "J": 0.2496,
          "CT": 0.0677,
          "CP": 0.0315,
          "eta": 0.5369
        },
        {
          "kind": "dynamic",
          "rpm": 3035.0,
          "J": 0.2856,
          "CT": 0.0627,
          "CP": 0.0307,
          "eta": 0.5836
        },
        {
          "kind": "dynamic",
          "rpm": 3035.0,
          "J": 0.3212,
          "CT": 0.0578,
          "CP": 0.0297,
          "eta": 0.6247
        },
        {
          "kind": "dynamic",
          "rpm": 3035.0,
          "J": 0.3578,
          "CT": 0.0516,
          "CP": 0.0282,
          "eta": 0.6534
        },
        {
          "kind": "dynamic",
          "rpm": 3035.0,
          "J": 0.3931,
          "CT": 0.0441,
          "CP": 0.0259,
          "eta": 0.6687
        },
        {
          "kind": "dynamic",
          "rpm": 3035.0,
          "J": 0.4329,
          "CT": 0.0354,
          "CP": 0.0229,
          "eta": 0.6699
        },
        {
          "kind": "dynamic",
          "rpm": 3035.0,
          "J": 0.4696,
          "CT": 0.0283,
          "CP": 0.0202,
          "eta": 0.6577
        },
        {
          "kind": "dynamic",
          "rpm": 3035.0,
          "J": 0.5091,
          "CT": 0.0197,
          "CP": 0.0166,
          "eta": 0.6032
        },
        {
          "kind": "dynamic",
          "rpm": 3035.0,
          "J": 0.5479,
          "CT": 0.0111,
          "CP": 0.0127,
          "eta": 0.4803
        },
        {
          "kind": "dynamic",
          "rpm": 3035.0,
          "J": 0.5824,
          "CT": 0.0037,
          "CP": 0.0092,
          "eta": 0.2324
        },
        {
          "kind": "dynamic",
          "rpm": 3035.0,
          "J": 0.5824,
          "CT": 0.0037,
          "CP": 0.0092,
          "eta": 0.2324
        },
        {
          "kind": "dynamic",
          "rpm": 3035.0,
          "J": 0.5824,
          "CT": 0.0037,
          "CP": 0.0092,
          "eta": 0.2324
        },
        {
          "kind": "dynamic",
          "rpm": 3035.0,
          "J": 0.5824,
          "CT": 0.0037,
          "CP": 0.0092,
          "eta": 0.2324
        },
        {
          "kind": "dynamic",
          "rpm": 3035.0,
          "J": 0.584,
          "CT": 0.0036,
          "CP": 0.0092,
          "eta": 0.2305
        },
        {
          "kind": "dynamic",
          "rpm": 4005.0,
          "J": 0.1024,
          "CT": 0.088,
          "CP": 0.0313,
          "eta": 0.2878
        },
        {
          "kind": "dynamic",
          "rpm": 4005.0,
          "J": 0.1319,
          "CT": 0.0857,
          "CP": 0.0317,
          "eta": 0.3567
        },
        {
          "kind": "dynamic",
          "rpm": 4005.0,
          "J": 0.1583,
          "CT": 0.083,
          "CP": 0.032,
          "eta": 0.4114
        },
        {
          "kind": "dynamic",
          "rpm": 4005.0,
          "J": 0.1861,
          "CT": 0.0795,
          "CP": 0.032,
          "eta": 0.4619
        },
        {
          "kind": "dynamic",
          "rpm": 4005.0,
          "J": 0.2156,
          "CT": 0.0751,
          "CP": 0.0317,
          "eta": 0.5099
        },
        {
          "kind": "dynamic",
          "rpm": 4005.0,
          "J": 0.2432,
          "CT": 0.0722,
          "CP": 0.0317,
          "eta": 0.5533
        },
        {
          "kind": "dynamic",
          "rpm": 4005.0,
          "J": 0.2715,
          "CT": 0.0682,
          "CP": 0.0313,
          "eta": 0.5929
        },
        {
          "kind": "dynamic",
          "rpm": 4005.0,
          "J": 0.2985,
          "CT": 0.0645,
          "CP": 0.0308,
          "eta": 0.6256
        },
        {
          "kind": "dynamic",
          "rpm": 4005.0,
          "J": 0.3241,
          "CT": 0.0597,
          "CP": 0.0298,
          "eta": 0.6507
        },
        {
          "kind": "dynamic",
          "rpm": 4005.0,
          "J": 0.3518,
          "CT": 0.0561,
          "CP": 0.0292,
          "eta": 0.6768
        },
        {
          "kind": "dynamic",
          "rpm": 4005.0,
          "J": 0.3796,
          "CT": 0.0521,
          "CP": 0.0283,
          "eta": 0.6989
        },
        {
          "kind": "dynamic",
          "rpm": 4005.0,
          "J": 0.4064,
          "CT": 0.0472,
          "CP": 0.0269,
          "eta": 0.7122
        },
        {
          "kind": "dynamic",
          "rpm": 4005.0,
          "J": 0.4335,
          "CT": 0.0427,
          "CP": 0.0256,
          "eta": 0.7228
        },
        {
          "kind": "dynamic",
          "rpm": 4005.0,
          "J": 0.4596,
          "CT": 0.037,
          "CP": 0.0236,
          "eta": 0.7209
        },
        {
          "kind": "dynamic",
          "rpm": 4005.0,
          "J": 0.4905,
          "CT": 0.0303,
          "CP": 0.0211,
          "eta": 0.7058
        },
        {
          "kind": "dynamic",
          "rpm": 4005.0,
          "J": 0.5181,
          "CT": 0.0237,
          "CP": 0.0183,
          "eta": 0.6717
        },
        {
          "kind": "dynamic",
          "rpm": 4005.0,
          "J": 0.5464,
          "CT": 0.0176,
          "CP": 0.0157,
          "eta": 0.613
        },
        {
          "kind": "dynamic",
          "rpm": 4043.0,
          "J": 0.4599,
          "CT": 0.037,
          "CP": 0.0235,
          "eta": 0.7249
        },
        {
          "kind": "dynamic",
          "rpm": 4043.0,
          "J": 0.4869,
          "CT": 0.0311,
          "CP": 0.0213,
          "eta": 0.7129
        },
        {
          "kind": "dynamic",
          "rpm": 4043.0,
          "J": 0.5181,
          "CT": 0.0243,
          "CP": 0.0185,
          "eta": 0.6809
        },
        {
          "kind": "dynamic",
          "rpm": 4043.0,
          "J": 0.5458,
          "CT": 0.018,
          "CP": 0.0158,
          "eta": 0.6229
        },
        {
          "kind": "dynamic",
          "rpm": 4043.0,
          "J": 0.5722,
          "CT": 0.0113,
          "CP": 0.0128,
          "eta": 0.5088
        },
        {
          "kind": "dynamic",
          "rpm": 4043.0,
          "J": 0.6013,
          "CT": 0.0043,
          "CP": 0.0095,
          "eta": 0.2753
        },
        {
          "kind": "dynamic",
          "rpm": 4043.0,
          "J": 0.6294,
          "CT": -0.0019,
          "CP": 0.0064,
          "eta": -0.1885
        },
        {
          "kind": "dynamic",
          "rpm": 4043.0,
          "J": 0.6294,
          "CT": -0.0019,
          "CP": 0.0064,
          "eta": -0.1885
        },
        {
          "kind": "dynamic",
          "rpm": 4043.0,
          "J": 0.6294,
          "CT": -0.0019,
          "CP": 0.0064,
          "eta": -0.1885
        },
        {
          "kind": "dynamic",
          "rpm": 4043.0,
          "J": 0.6294,
          "CT": -0.0019,
          "CP": 0.0064,
          "eta": -0.1885
        },
        {
          "kind": "dynamic",
          "rpm": 4043.0,
          "J": 0.6294,
          "CT": -0.0019,
          "CP": 0.0064,
          "eta": -0.1885
        },
        {
          "kind": "dynamic",
          "rpm": 4043.0,
          "J": 0.6294,
          "CT": -0.0019,
          "CP": 0.0064,
          "eta": -0.1885
        },
        {
          "kind": "dynamic",
          "rpm": 4043.0,
          "J": 0.6294,
          "CT": -0.0019,
          "CP": 0.0064,
          "eta": -0.1885
        },
        {
          "kind": "dynamic",
          "rpm": 4043.0,
          "J": 0.6294,
          "CT": -0.0019,
          "CP": 0.0064,
          "eta": -0.1885
        },
        {
          "kind": "dynamic",
          "rpm": 4043.0,
          "J": 0.6294,
          "CT": -0.0019,
          "CP": 0.0064,
          "eta": -0.1885
        },
        {
          "kind": "dynamic",
          "rpm": 4043.0,
          "J": 0.6294,
          "CT": -0.0019,
          "CP": 0.0064,
          "eta": -0.1885
        },
        {
          "kind": "dynamic",
          "rpm": 4043.0,
          "J": 0.6294,
          "CT": -0.0019,
          "CP": 0.0064,
          "eta": -0.1885
        },
        {
          "kind": "dynamic",
          "rpm": 4043.0,
          "J": 0.6294,
          "CT": -0.0019,
          "CP": 0.0064,
          "eta": -0.1885
        },
        {
          "kind": "dynamic",
          "rpm": 4043.0,
          "J": 0.6294,
          "CT": -0.0019,
          "CP": 0.0064,
          "eta": -0.1885
        },
        {
          "kind": "dynamic",
          "rpm": 4043.0,
          "J": 0.6294,
          "CT": -0.0019,
          "CP": 0.0064,
          "eta": -0.1885
        },
        {
          "kind": "dynamic",
          "rpm": 4043.0,
          "J": 0.6294,
          "CT": -0.0019,
          "CP": 0.0064,
          "eta": -0.1885
        },
        {
          "kind": "dynamic",
          "rpm": 4043.0,
          "J": 0.6294,
          "CT": -0.0019,
          "CP": 0.0064,
          "eta": -0.1885
        },
        {
          "kind": "dynamic",
          "rpm": 4043.0,
          "J": 0.6294,
          "CT": -0.0019,
          "CP": 0.0064,
          "eta": -0.1885
        },
        {
          "kind": "dynamic",
          "rpm": 4043.0,
          "J": 0.6298,
          "CT": -0.0019,
          "CP": 0.0065,
          "eta": -0.1866
        },
        {
          "kind": "dynamic",
          "rpm": 4993.0,
          "J": 0.1016,
          "CT": 0.0896,
          "CP": 0.0318,
          "eta": 0.2867
        },
        {
          "kind": "dynamic",
          "rpm": 4993.0,
          "J": 0.1253,
          "CT": 0.0876,
          "CP": 0.0319,
          "eta": 0.3443
        },
        {
          "kind": "dynamic",
          "rpm": 4993.0,
          "J": 0.1461,
          "CT": 0.0852,
          "CP": 0.0319,
          "eta": 0.3905
        },
        {
          "kind": "dynamic",
          "rpm": 4993.0,
          "J": 0.1665,
          "CT": 0.0831,
          "CP": 0.032,
          "eta": 0.4326
        },
        {
          "kind": "dynamic",
          "rpm": 4993.0,
          "J": 0.1917,
          "CT": 0.0802,
          "CP": 0.032,
          "eta": 0.4811
        },
        {
          "kind": "dynamic",
          "rpm": 4993.0,
          "J": 0.2134,
          "CT": 0.0772,
          "CP": 0.0318,
          "eta": 0.5179
        },
        {
          "kind": "dynamic",
          "rpm": 4993.0,
          "J": 0.2378,
          "CT": 0.0747,
          "CP": 0.0319,
          "eta": 0.557
        },
        {
          "kind": "dynamic",
          "rpm": 4993.0,
          "J": 0.2594,
          "CT": 0.0719,
          "CP": 0.0317,
          "eta": 0.588
        },
        {
          "kind": "dynamic",
          "rpm": 4993.0,
          "J": 0.2813,
          "CT": 0.0686,
          "CP": 0.0313,
          "eta": 0.6153
        },
        {
          "kind": "dynamic",
          "rpm": 4993.0,
          "J": 0.3036,
          "CT": 0.0651,
          "CP": 0.0309,
          "eta": 0.64
        },
        {
          "kind": "dynamic",
          "rpm": 4993.0,
          "J": 0.3258,
          "CT": 0.0616,
          "CP": 0.0304,
          "eta": 0.6613
        },
        {
          "kind": "dynamic",
          "rpm": 4993.0,
          "J": 0.3486,
          "CT": 0.0583,
          "CP": 0.0299,
          "eta": 0.6801
        },
        {
          "kind": "dynamic",
          "rpm": 4993.0,
          "J": 0.3705,
          "CT": 0.0545,
          "CP": 0.0291,
          "eta": 0.6948
        },
        {
          "kind": "dynamic",
          "rpm": 4993.0,
          "J": 0.3931,
          "CT": 0.0513,
          "CP": 0.0284,
          "eta": 0.7106
        },
        {
          "kind": "dynamic",
          "rpm": 4993.0,
          "J": 0.4136,
          "CT": 0.0475,
          "CP": 0.0274,
          "eta": 0.7181
        },
        {
          "kind": "dynamic",
          "rpm": 4993.0,
          "J": 0.4355,
          "CT": 0.0437,
          "CP": 0.0263,
          "eta": 0.7248
        },
        {
          "kind": "dynamic",
          "rpm": 5049.0,
          "J": 0.3708,
          "CT": 0.0548,
          "CP": 0.029,
          "eta": 0.6995
        },
        {
          "kind": "dynamic",
          "rpm": 5049.0,
          "J": 0.3931,
          "CT": 0.0511,
          "CP": 0.0282,
          "eta": 0.7122
        },
        {
          "kind": "dynamic",
          "rpm": 5049.0,
          "J": 0.4148,
          "CT": 0.0475,
          "CP": 0.0273,
          "eta": 0.7232
        },
        {
          "kind": "dynamic",
          "rpm": 5049.0,
          "J": 0.436,
          "CT": 0.0436,
          "CP": 0.0261,
          "eta": 0.7282
        },
        {
          "kind": "dynamic",
          "rpm": 5049.0,
          "J": 0.4578,
          "CT": 0.04,
          "CP": 0.025,
          "eta": 0.7315
        },
        {
          "kind": "dynamic",
          "rpm": 5049.0,
          "J": 0.4796,
          "CT": 0.036,
          "CP": 0.0237,
          "eta": 0.7293
        },
        {
          "kind": "dynamic",
          "rpm": 5049.0,
          "J": 0.5006,
          "CT": 0.032,
          "CP": 0.0221,
          "eta": 0.724
        },
        {
          "kind": "dynamic",
          "rpm": 5049.0,
          "J": 0.5216,
          "CT": 0.0281,
          "CP": 0.0205,
          "eta": 0.7155
        },
        {
          "kind": "dynamic",
          "rpm": 5049.0,
          "J": 0.5462,
          "CT": 0.0233,
          "CP": 0.0186,
          "eta": 0.6857
        },
        {
          "kind": "dynamic",
          "rpm": 5049.0,
          "J": 0.5709,
          "CT": 0.0179,
          "CP": 0.0163,
          "eta": 0.6282
        },
        {
          "kind": "dynamic",
          "rpm": 5049.0,
          "J": 0.5905,
          "CT": 0.0126,
          "CP": 0.0138,
          "eta": 0.5391
        },
        {
          "kind": "dynamic",
          "rpm": 5049.0,
          "J": 0.6128,
          "CT": 0.0076,
          "CP": 0.0115,
          "eta": 0.4065
        },
        {
          "kind": "dynamic",
          "rpm": 5049.0,
          "J": 0.6356,
          "CT": 0.0022,
          "CP": 0.0089,
          "eta": 0.1597
        },
        {
          "kind": "dynamic",
          "rpm": 5049.0,
          "J": 0.6564,
          "CT": -0.0031,
          "CP": 0.0062,
          "eta": -0.3278
        },
        {
          "kind": "dynamic",
          "rpm": 5049.0,
          "J": 0.6564,
          "CT": -0.0031,
          "CP": 0.0062,
          "eta": -0.3278
        },
        {
          "kind": "dynamic",
          "rpm": 5049.0,
          "J": 0.6564,
          "CT": -0.0031,
          "CP": 0.0062,
          "eta": -0.3278
        },
        {
          "kind": "dynamic",
          "rpm": 5049.0,
          "J": 0.6564,
          "CT": -0.0031,
          "CP": 0.0062,
          "eta": -0.3278
        },
        {
          "kind": "dynamic",
          "rpm": 5049.0,
          "J": 0.6564,
          "CT": -0.0031,
          "CP": 0.0062,
          "eta": -0.3278
        },
        {
          "kind": "dynamic",
          "rpm": 5049.0,
          "J": 0.6564,
          "CT": -0.0031,
          "CP": 0.0062,
          "eta": -0.3278
        },
        {
          "kind": "dynamic",
          "rpm": 5049.0,
          "J": 0.6564,
          "CT": -0.0031,
          "CP": 0.0062,
          "eta": -0.3278
        },
        {
          "kind": "dynamic",
          "rpm": 5049.0,
          "J": 0.6564,
          "CT": -0.0031,
          "CP": 0.0062,
          "eta": -0.3278
        },
        {
          "kind": "dynamic",
          "rpm": 5049.0,
          "J": 0.6564,
          "CT": -0.0031,
          "CP": 0.0062,
          "eta": -0.3278
        },
        {
          "kind": "dynamic",
          "rpm": 5049.0,
          "J": 0.6564,
          "CT": -0.0031,
          "CP": 0.0062,
          "eta": -0.3278
        },
        {
          "kind": "dynamic",
          "rpm": 5049.0,
          "J": 0.6571,
          "CT": -0.0031,
          "CP": 0.0063,
          "eta": -0.3238
        },
        {
          "kind": "dynamic",
          "rpm": 5978.0,
          "J": 0.1021,
          "CT": 0.0916,
          "CP": 0.0324,
          "eta": 0.2885
        },
        {
          "kind": "dynamic",
          "rpm": 5978.0,
          "J": 0.1203,
          "CT": 0.09,
          "CP": 0.0325,
          "eta": 0.333
        },
        {
          "kind": "dynamic",
          "rpm": 5978.0,
          "J": 0.1408,
          "CT": 0.088,
          "CP": 0.0326,
          "eta": 0.38
        },
        {
          "kind": "dynamic",
          "rpm": 5978.0,
          "J": 0.157,
          "CT": 0.0862,
          "CP": 0.0326,
          "eta": 0.4154
        },
        {
          "kind": "dynamic",
          "rpm": 5978.0,
          "J": 0.1782,
          "CT": 0.0844,
          "CP": 0.0328,
          "eta": 0.4587
        },
        {
          "kind": "dynamic",
          "rpm": 5978.0,
          "J": 0.1961,
          "CT": 0.0823,
          "CP": 0.0328,
          "eta": 0.4924
        },
        {
          "kind": "dynamic",
          "rpm": 5978.0,
          "J": 0.2154,
          "CT": 0.0797,
          "CP": 0.0325,
          "eta": 0.5274
        },
        {
          "kind": "dynamic",
          "rpm": 5978.0,
          "J": 0.2326,
          "CT": 0.0771,
          "CP": 0.0323,
          "eta": 0.5551
        },
        {
          "kind": "dynamic",
          "rpm": 5978.0,
          "J": 0.2524,
          "CT": 0.075,
          "CP": 0.0323,
          "eta": 0.5856
        },
        {
          "kind": "dynamic",
          "rpm": 5978.0,
          "J": 0.2699,
          "CT": 0.0717,
          "CP": 0.0318,
          "eta": 0.6081
        },
        {
          "kind": "dynamic",
          "rpm": 5978.0,
          "J": 0.2886,
          "CT": 0.0692,
          "CP": 0.0317,
          "eta": 0.6313
        },
        {
          "kind": "dynamic",
          "rpm": 5978.0,
          "J": 0.3078,
          "CT": 0.0661,
          "CP": 0.0311,
          "eta": 0.6531
        },
        {
          "kind": "dynamic",
          "rpm": 5978.0,
          "J": 0.3263,
          "CT": 0.0633,
          "CP": 0.0307,
          "eta": 0.672
        },
        {
          "kind": "dynamic",
          "rpm": 5978.0,
          "J": 0.3454,
          "CT": 0.0603,
          "CP": 0.0302,
          "eta": 0.6884
        },
        {
          "kind": "dynamic",
          "rpm": 5978.0,
          "J": 0.3633,
          "CT": 0.0576,
          "CP": 0.0298,
          "eta": 0.7026
        },
        {
          "kind": "dynamic",
          "rpm": 6028.0,
          "J": 0.3089,
          "CT": 0.0659,
          "CP": 0.0309,
          "eta": 0.6595
        },
        {
          "kind": "dynamic",
          "rpm": 6028.0,
          "J": 0.3275,
          "CT": 0.0633,
          "CP": 0.0305,
          "eta": 0.6789
        },
        {
          "kind": "dynamic",
          "rpm": 6028.0,
          "J": 0.3466,
          "CT": 0.0602,
          "CP": 0.03,
          "eta": 0.695
        },
        {
          "kind": "dynamic",
          "rpm": 6028.0,
          "J": 0.364,
          "CT": 0.057,
          "CP": 0.0294,
          "eta": 0.7064
        },
        {
          "kind": "dynamic",
          "rpm": 6028.0,
          "J": 0.3835,
          "CT": 0.0544,
          "CP": 0.029,
          "eta": 0.7182
        },
        {
          "kind": "dynamic",
          "rpm": 6028.0,
          "J": 0.4004,
          "CT": 0.0511,
          "CP": 0.0282,
          "eta": 0.7254
        },
        {
          "kind": "dynamic",
          "rpm": 6028.0,
          "J": 0.419,
          "CT": 0.0479,
          "CP": 0.0273,
          "eta": 0.7334
        },
        {
          "kind": "dynamic",
          "rpm": 6028.0,
          "J": 0.4368,
          "CT": 0.0446,
          "CP": 0.0264,
          "eta": 0.7376
        },
        {
          "kind": "dynamic",
          "rpm": 6028.0,
          "J": 0.4541,
          "CT": 0.0412,
          "CP": 0.0254,
          "eta": 0.7385
        },
        {
          "kind": "dynamic",
          "rpm": 6028.0,
          "J": 0.4742,
          "CT": 0.0381,
          "CP": 0.0244,
          "eta": 0.7405
        },
        {
          "kind": "dynamic",
          "rpm": 6028.0,
          "J": 0.4912,
          "CT": 0.0347,
          "CP": 0.0232,
          "eta": 0.7346
        },
        {
          "kind": "dynamic",
          "rpm": 6028.0,
          "J": 0.5109,
          "CT": 0.0313,
          "CP": 0.022,
          "eta": 0.7255
        },
        {
          "kind": "dynamic",
          "rpm": 6028.0,
          "J": 0.5292,
          "CT": 0.0278,
          "CP": 0.0207,
          "eta": 0.7106
        },
        {
          "kind": "dynamic",
          "rpm": 6028.0,
          "J": 0.5481,
          "CT": 0.0242,
          "CP": 0.0191,
          "eta": 0.6952
        },
        {
          "kind": "dynamic",
          "rpm": 6028.0,
          "J": 0.5652,
          "CT": 0.021,
          "CP": 0.0177,
          "eta": 0.669
        },
        {
          "kind": "dynamic",
          "rpm": 6028.0,
          "J": 0.5835,
          "CT": 0.0171,
          "CP": 0.0161,
          "eta": 0.6216
        },
        {
          "kind": "dynamic",
          "rpm": 6028.0,
          "J": 0.6013,
          "CT": 0.0137,
          "CP": 0.0144,
          "eta": 0.5699
        },
        {
          "kind": "dynamic",
          "rpm": 6028.0,
          "J": 0.6204,
          "CT": 0.0098,
          "CP": 0.0127,
          "eta": 0.4795
        },
        {
          "kind": "dynamic",
          "rpm": 6028.0,
          "J": 0.6407,
          "CT": 0.0051,
          "CP": 0.0104,
          "eta": 0.313
        },
        {
          "kind": "dynamic",
          "rpm": 6028.0,
          "J": 0.6575,
          "CT": 0.0012,
          "CP": 0.0085,
          "eta": 0.0956
        },
        {
          "kind": "dynamic",
          "rpm": 6028.0,
          "J": 0.6776,
          "CT": -0.0034,
          "CP": 0.0063,
          "eta": -0.3609
        },
        {
          "kind": "dynamic",
          "rpm": 6028.0,
          "J": 0.6777,
          "CT": -0.0034,
          "CP": 0.0063,
          "eta": -0.3618
        },
        {
          "kind": "dynamic",
          "rpm": 6028.0,
          "J": 0.6777,
          "CT": -0.0034,
          "CP": 0.0063,
          "eta": -0.3618
        },
        {
          "kind": "dynamic",
          "rpm": 6028.0,
          "J": 0.6777,
          "CT": -0.0034,
          "CP": 0.0063,
          "eta": -0.3618
        },
        {
          "kind": "dynamic",
          "rpm": 7009.0,
          "J": 0.0851,
          "CT": 0.0958,
          "CP": 0.0334,
          "eta": 0.2445
        },
        {
          "kind": "dynamic",
          "rpm": 7009.0,
          "J": 0.1009,
          "CT": 0.0952,
          "CP": 0.0338,
          "eta": 0.2846
        },
        {
          "kind": "dynamic",
          "rpm": 7009.0,
          "J": 0.1167,
          "CT": 0.0936,
          "CP": 0.0337,
          "eta": 0.324
        },
        {
          "kind": "dynamic",
          "rpm": 7009.0,
          "J": 0.1314,
          "CT": 0.0923,
          "CP": 0.0337,
          "eta": 0.3597
        },
        {
          "kind": "dynamic",
          "rpm": 7009.0,
          "J": 0.1499,
          "CT": 0.0904,
          "CP": 0.0338,
          "eta": 0.4016
        },
        {
          "kind": "dynamic",
          "rpm": 7009.0,
          "J": 0.1664,
          "CT": 0.089,
          "CP": 0.0339,
          "eta": 0.4368
        },
        {
          "kind": "dynamic",
          "rpm": 7009.0,
          "J": 0.1817,
          "CT": 0.0869,
          "CP": 0.0338,
          "eta": 0.4681
        },
        {
          "kind": "dynamic",
          "rpm": 7009.0,
          "J": 0.1973,
          "CT": 0.085,
          "CP": 0.0336,
          "eta": 0.4986
        },
        {
          "kind": "dynamic",
          "rpm": 7009.0,
          "J": 0.2132,
          "CT": 0.0827,
          "CP": 0.0334,
          "eta": 0.5277
        },
        {
          "kind": "dynamic",
          "rpm": 7009.0,
          "J": 0.2282,
          "CT": 0.081,
          "CP": 0.0334,
          "eta": 0.5538
        },
        {
          "kind": "dynamic",
          "rpm": 7009.0,
          "J": 0.2456,
          "CT": 0.0787,
          "CP": 0.0332,
          "eta": 0.5819
        },
        {
          "kind": "dynamic",
          "rpm": 7009.0,
          "J": 0.2597,
          "CT": 0.0765,
          "CP": 0.033,
          "eta": 0.6025
        },
        {
          "kind": "dynamic",
          "rpm": 7009.0,
          "J": 0.2759,
          "CT": 0.0742,
          "CP": 0.0328,
          "eta": 0.625
        },
        {
          "kind": "dynamic",
          "rpm": 7009.0,
          "J": 0.2911,
          "CT": 0.0713,
          "CP": 0.0323,
          "eta": 0.643
        },
        {
          "kind": "dynamic",
          "rpm": 7009.0,
          "J": 0.3079,
          "CT": 0.0692,
          "CP": 0.0321,
          "eta": 0.6632
        },
        {
          "kind": "dynamic",
          "rpm": 7042.0,
          "J": 0.2601,
          "CT": 0.0767,
          "CP": 0.0328,
          "eta": 0.6086
        },
        {
          "kind": "dynamic",
          "rpm": 7042.0,
          "J": 0.2766,
          "CT": 0.0741,
          "CP": 0.0325,
          "eta": 0.6303
        },
        {
          "kind": "dynamic",
          "rpm": 7042.0,
          "J": 0.2926,
          "CT": 0.0716,
          "CP": 0.0322,
          "eta": 0.6506
        },
        {
          "kind": "dynamic",
          "rpm": 7042.0,
          "J": 0.3082,
          "CT": 0.0689,
          "CP": 0.0318,
          "eta": 0.6683
        },
        {
          "kind": "dynamic",
          "rpm": 7042.0,
          "J": 0.3244,
          "CT": 0.0663,
          "CP": 0.0314,
          "eta": 0.6859
        },
        {
          "kind": "dynamic",
          "rpm": 7042.0,
          "J": 0.3402,
          "CT": 0.0636,
          "CP": 0.0309,
          "eta": 0.7009
        },
        {
          "kind": "dynamic",
          "rpm": 7042.0,
          "J": 0.3555,
          "CT": 0.0612,
          "CP": 0.0305,
          "eta": 0.7147
        },
        {
          "kind": "dynamic",
          "rpm": 7042.0,
          "J": 0.371,
          "CT": 0.0583,
          "CP": 0.0299,
          "eta": 0.7247
        },
        {
          "kind": "dynamic",
          "rpm": 7042.0,
          "J": 0.3879,
          "CT": 0.0553,
          "CP": 0.0292,
          "eta": 0.7357
        },
        {
          "kind": "dynamic",
          "rpm": 7042.0,
          "J": 0.4035,
          "CT": 0.0527,
          "CP": 0.0286,
          "eta": 0.7436
        },
        {
          "kind": "dynamic",
          "rpm": 7042.0,
          "J": 0.4203,
          "CT": 0.0496,
          "CP": 0.0278,
          "eta": 0.7498
        },
        {
          "kind": "dynamic",
          "rpm": 7042.0,
          "J": 0.4363,
          "CT": 0.0464,
          "CP": 0.0269,
          "eta": 0.753
        },
        {
          "kind": "dynamic",
          "rpm": 7042.0,
          "J": 0.4525,
          "CT": 0.0435,
          "CP": 0.026,
          "eta": 0.7563
        },
        {
          "kind": "dynamic",
          "rpm": 7042.0,
          "J": 0.469,
          "CT": 0.0405,
          "CP": 0.0251,
          "eta": 0.7566
        },
        {
          "kind": "dynamic",
          "rpm": 7042.0,
          "J": 0.4827,
          "CT": 0.0379,
          "CP": 0.0242,
          "eta": 0.7563
        },
        {
          "kind": "dynamic",
          "rpm": 7042.0,
          "J": 0.4999,
          "CT": 0.0344,
          "CP": 0.023,
          "eta": 0.7479
        },
        {
          "kind": "dynamic",
          "rpm": 7042.0,
          "J": 0.5153,
          "CT": 0.0314,
          "CP": 0.0219,
          "eta": 0.7393
        },
        {
          "kind": "dynamic",
          "rpm": 7042.0,
          "J": 0.5305,
          "CT": 0.0286,
          "CP": 0.0208,
          "eta": 0.7278
        },
        {
          "kind": "dynamic",
          "rpm": 7042.0,
          "J": 0.5494,
          "CT": 0.025,
          "CP": 0.0194,
          "eta": 0.7061
        },
        {
          "kind": "dynamic",
          "rpm": 7042.0,
          "J": 0.5623,
          "CT": 0.0222,
          "CP": 0.0182,
          "eta": 0.6851
        },
        {
          "kind": "dynamic",
          "rpm": 7042.0,
          "J": 0.5782,
          "CT": 0.0193,
          "CP": 0.017,
          "eta": 0.6586
        },
        {
          "kind": "dynamic",
          "rpm": 7042.0,
          "J": 0.5963,
          "CT": 0.0157,
          "CP": 0.0154,
          "eta": 0.6085
        },
        {
          "kind": "dynamic",
          "rpm": 7042.0,
          "J": 0.6124,
          "CT": 0.0125,
          "CP": 0.0139,
          "eta": 0.55
        },
        {
          "kind": "dynamic",
          "rpm": 7042.0,
          "J": 0.6291,
          "CT": 0.009,
          "CP": 0.0122,
          "eta": 0.4645
        },
        {
          "kind": "static",
          "rpm": 1013.0,
          "J": 0.0,
          "CT": 0.0786,
          "CP": 0.0351,
          "eta": 0.0
        },
        {
          "kind": "static",
          "rpm": 1466.0,
          "J": 0.0,
          "CT": 0.0812,
          "CP": 0.0335,
          "eta": 0.0
        },
        {
          "kind": "static",
          "rpm": 2033.0,
          "J": 0.0,
          "CT": 0.086,
          "CP": 0.0321,
          "eta": 0.0
        },
        {
          "kind": "static",
          "rpm": 2513.0,
          "J": 0.0,
          "CT": 0.0887,
          "CP": 0.031,
          "eta": 0.0
        },
        {
          "kind": "static",
          "rpm": 2966.0,
          "J": 0.0,
          "CT": 0.0909,
          "CP": 0.0304,
          "eta": 0.0
        },
        {
          "kind": "static",
          "rpm": 3453.0,
          "J": 0.0,
          "CT": 0.0921,
          "CP": 0.0301,
          "eta": 0.0
        },
        {
          "kind": "static",
          "rpm": 3980.0,
          "J": 0.0,
          "CT": 0.0933,
          "CP": 0.0303,
          "eta": 0.0
        },
        {
          "kind": "static",
          "rpm": 4486.0,
          "J": 0.0,
          "CT": 0.0937,
          "CP": 0.0303,
          "eta": 0.0
        },
        {
          "kind": "static",
          "rpm": 4953.0,
          "J": 0.0,
          "CT": 0.0941,
          "CP": 0.0308,
          "eta": 0.0
        },
        {
          "kind": "static",
          "rpm": 5546.0,
          "J": 0.0,
          "CT": 0.0952,
          "CP": 0.0312,
          "eta": 0.0
        },
        {
          "kind": "static",
          "rpm": 6026.0,
          "J": 0.0,
          "CT": 0.0956,
          "CP": 0.0316,
          "eta": 0.0
        },
        {
          "kind": "static",
          "rpm": 6453.0,
          "J": 0.0,
          "CT": 0.0971,
          "CP": 0.032,
          "eta": 0.0
        },
        {
          "kind": "static",
          "rpm": 6986.0,
          "J": 0.0,
          "CT": 0.0991,
          "CP": 0.0325,
          "eta": 0.0
        },
        {
          "kind": "static",
          "rpm": 7453.0,
          "J": 0.0,
          "CT": 0.1003,
          "CP": 0.0331,
          "eta": 0.0
        }
      ]
    }
  }
}