{
  "meta": {
    "name": "apcff_4.2x4",
    "diameter_in": 4.2,
    "pitch_in": 4.0,
    "blades": 2,
    "type": null,
    "apc_name": null,
    "uiuc_name": "apcff_4.2x4",
    "has_simulated": false,
    "has_empirical": true
  },
  "sources": {
    "simulated": null,
    "empirical": {
      "rpm_min": 1490,
      "rpm_max": 10071,
      "n_points": 102,
      "volumes": [
        "volume-2"
      ],
      "geometry": [
        {
          "r_R": 0.15,
          "c_R": 0.2027,
          "beta": 38.363
        },
        {
          "r_R": 0.2,
          "c_R": 0.1909,
          "beta": 42.864
        },
        {
          "r_R": 0.25,
          "c_R": 0.1865,
          "beta": 45.208
        },
        {
          "r_R": 0.3,
          "c_R": 0.1823,
          "beta": 44.502
        },
        {
          "r_R": 0.35,
          "c_R": 0.18,
          "beta": 42.724
        },
        {
          "r_R": 0.4,
          "c_R": 0.1817,
          "beta": 40.263
        },
        {
          "r_R": 0.45,
          "c_R": 0.186,
          "beta": 37.416
        },
        {
          "r_R": 0.5,
          "c_R": 0.1895,
          "beta": 34.613
        },
        {
          "r_R": 0.55,
          "c_R": 0.1902,
          "beta": 32.197
        },
        {
          "r_R": 0.6,
          "c_R": 0.188,
          "beta": 30.083
        },
        {
          "r_R": 0.65,
          "c_R": 0.183,
          "beta": 28.195
        },
        {
          "r_R": 0.7,
          "c_R": 0.175,
          "beta": 26.509
        },
        {
          "r_R": 0.75,
          "c_R": 0.1642,
          "beta": 24.943
        },
        {
          "r_R": 0.8,
          "c_R": 0.1506,
          "beta": 23.468
        },
        {
          "r_R": 0.85,
          "c_R": 0.1341,
          "beta": 21.855
        },
        {
          "r_R": 0.9,
          "c_R": 0.1145,
          "beta": 19.775
        },
        {
          "r_R": 0.95,
          "c_R": 0.0855,
          "beta": 17.162
        },
        {
          "r_R": 1.0,
          "c_R": 0.009,
          "beta": 15.732
        }
      ],
      "sweep": [
        {
          "kind": "dynamic",
          "rpm": 6043.0,
          "J": 0.1136,
          "CT": 0.1282,
          "CP": 0.1124,
          "eta": 0.1295
        },
        {
          "kind": "dynamic",
          "rpm": 6043.0,
          "J": 0.1706,
          "CT": 0.1263,
          "CP": 0.112,
          "eta": 0.1923
        },
        {
          "kind": "dynamic",
          "rpm": 6043.0,
          "J": 0.2271,
          "CT": 0.1224,
          "CP": 0.1096,
          "eta": 0.2536
        },
        {
          "kind": "dynamic",
          "rpm": 6043.0,
          "J": 0.2804,
          "CT": 0.1172,
          "CP": 0.1066,
          "eta": 0.3082
        },
        {
          "kind": "dynamic",
          "rpm": 6043.0,
          "J": 0.3376,
          "CT": 0.1121,
          "CP": 0.1042,
          "eta": 0.363
        },
        {
          "kind": "dynamic",
          "rpm": 6043.0,
          "J": 0.3907,
          "CT": 0.1065,
          "CP": 0.1011,
          "eta": 0.4117
        },
        {
          "kind": "dynamic",
          "rpm": 6043.0,
          "J": 0.4539,
          "CT": 0.0995,
          "CP": 0.0984,
          "eta": 0.4588
        },
        {
          "kind": "dynamic",
          "rpm": 6043.0,
          "J": 0.5106,
          "CT": 0.0917,
          "CP": 0.094,
          "eta": 0.4981
        },
        {
          "kind": "dynamic",
          "rpm": 6043.0,
          "J": 0.5639,
          "CT": 0.084,
          "CP": 0.0901,
          "eta": 0.5261
        },
        {
          "kind": "dynamic",
          "rpm": 6043.0,
          "J": 0.6254,
          "CT": 0.0756,
          "CP": 0.0857,
          "eta": 0.5518
        },
        {
          "kind": "dynamic",
          "rpm": 6043.0,
          "J": 0.6817,
          "CT": 0.0664,
          "CP": 0.0798,
          "eta": 0.5671
        },
        {
          "kind": "dynamic",
          "rpm": 6043.0,
          "J": 0.7385,
          "CT": 0.0557,
          "CP": 0.0715,
          "eta": 0.5744
        },
        {
          "kind": "dynamic",
          "rpm": 6043.0,
          "J": 0.7933,
          "CT": 0.0453,
          "CP": 0.0632,
          "eta": 0.5683
        },
        {
          "kind": "dynamic",
          "rpm": 6043.0,
          "J": 0.8508,
          "CT": 0.0344,
          "CP": 0.0547,
          "eta": 0.5346
        },
        {
          "kind": "dynamic",
          "rpm": 6043.0,
          "J": 0.9123,
          "CT": 0.0224,
          "CP": 0.0444,
          "eta": 0.4599
        },
        {
          "kind": "dynamic",
          "rpm": 6043.0,
          "J": 0.9624,
          "CT": 0.0115,
          "CP": 0.0354,
          "eta": 0.3136
        },
        {
          "kind": "dynamic",
          "rpm": 6043.0,
          "J": 1.0263,
          "CT": -0.0006,
          "CP": 0.0254,
          "eta": -0.0229
        },
        {
          "kind": "dynamic",
          "rpm": 6043.0,
          "J": 1.0751,
          "CT": -0.0109,
          "CP": 0.0156,
          "eta": -0.7526
        },
        {
          "kind": "dynamic",
          "rpm": 6043.0,
          "J": 1.1407,
          "CT": -0.0234,
          "CP": 0.0061,
          "eta": -4.3433
        },
        {
          "kind": "dynamic",
          "rpm": 8043.0,
          "J": 0.085,
          "CT": 0.1317,
          "CP": 0.1131,
          "eta": 0.099
        },
        {
          "kind": "dynamic",
          "rpm": 8043.0,
          "J": 0.1276,
          "CT": 0.129,
          "CP": 0.1119,
          "eta": 0.1472
        },
        {
          "kind": "dynamic",
          "rpm": 8043.0,
          "J": 0.1702,
          "CT": 0.1276,
          "CP": 0.1118,
          "eta": 0.1943
        },
        {
          "kind": "dynamic",
          "rpm": 8043.0,
          "J": 0.2127,
          "CT": 0.1255,
          "CP": 0.1108,
          "eta": 0.2408
        },
        {
          "kind": "dynamic",
          "rpm": 8043.0,
          "J": 0.2556,
          "CT": 0.1223,
          "CP": 0.1086,
          "eta": 0.2877
        },
        {
          "kind": "dynamic",
          "rpm": 8043.0,
          "J": 0.2957,
          "CT": 0.1181,
          "CP": 0.106,
          "eta": 0.3296
        },
        {
          "kind": "dynamic",
          "rpm": 8043.0,
          "J": 0.3387,
          "CT": 0.1143,
          "CP": 0.1041,
          "eta": 0.3719
        },
        {
          "kind": "dynamic",
          "rpm": 8043.0,
          "J": 0.3821,
          "CT": 0.1102,
          "CP": 0.1019,
          "eta": 0.4133
        },
        {
          "kind": "dynamic",
          "rpm": 8043.0,
          "J": 0.4234,
          "CT": 0.1063,
          "CP": 0.1,
          "eta": 0.4499
        },
        {
          "kind": "dynamic",
          "rpm": 8043.0,
          "J": 0.4695,
          "CT": 0.1015,
          "CP": 0.0979,
          "eta": 0.4865
        },
        {
          "kind": "dynamic",
          "rpm": 8043.0,
          "J": 0.5105,
          "CT": 0.0956,
          "CP": 0.0945,
          "eta": 0.5164
        },
        {
          "kind": "dynamic",
          "rpm": 8043.0,
          "J": 0.5553,
          "CT": 0.0902,
          "CP": 0.0921,
          "eta": 0.5437
        },
        {
          "kind": "dynamic",
          "rpm": 8043.0,
          "J": 0.5921,
          "CT": 0.0839,
          "CP": 0.0885,
          "eta": 0.5611
        },
        {
          "kind": "dynamic",
          "rpm": 8043.0,
          "J": 0.6374,
          "CT": 0.0781,
          "CP": 0.0856,
          "eta": 0.5814
        },
        {
          "kind": "dynamic",
          "rpm": 8043.0,
          "J": 0.6802,
          "CT": 0.0717,
          "CP": 0.0816,
          "eta": 0.5973
        },
        {
          "kind": "dynamic",
          "rpm": 8043.0,
          "J": 0.7218,
          "CT": 0.0641,
          "CP": 0.0763,
          "eta": 0.6066
        },
        {
          "kind": "dynamic",
          "rpm": 8043.0,
          "J": 0.7668,
          "CT": 0.0548,
          "CP": 0.0697,
          "eta": 0.603
        },
        {
          "kind": "dynamic",
          "rpm": 8043.0,
          "J": 0.81,
          "CT": 0.0452,
          "CP": 0.0626,
          "eta": 0.5853
        },
        {
          "kind": "dynamic",
          "rpm": 8043.0,
          "J": 0.8527,
          "CT": 0.0353,
          "CP": 0.0543,
          "eta": 0.554
        },
        {
          "kind": "dynamic",
          "rpm": 8067.0,
          "J": 0.7227,
          "CT": 0.0625,
          "CP": 0.075,
          "eta": 0.6025
        },
        {
          "kind": "dynamic",
          "rpm": 8067.0,
          "J": 0.757,
          "CT": 0.0567,
          "CP": 0.0711,
          "eta": 0.6036
        },
        {
          "kind": "dynamic",
          "rpm": 8067.0,
          "J": 0.8093,
          "CT": 0.0455,
          "CP": 0.0622,
          "eta": 0.5912
        },
        {
          "kind": "dynamic",
          "rpm": 8067.0,
          "J": 0.8517,
          "CT": 0.0352,
          "CP": 0.0539,
          "eta": 0.5554
        },
        {
          "kind": "dynamic",
          "rpm": 8067.0,
          "J": 0.8962,
          "CT": 0.0267,
          "CP": 0.0474,
          "eta": 0.5057
        },
        {
          "kind": "dynamic",
          "rpm": 8067.0,
          "J": 0.934,
          "CT": 0.0193,
          "CP": 0.0411,
          "eta": 0.4378
        },
        {
          "kind": "dynamic",
          "rpm": 8067.0,
          "J": 0.9754,
          "CT": 0.0104,
          "CP": 0.0337,
          "eta": 0.3011
        },
        {
          "kind": "dynamic",
          "rpm": 8067.0,
          "J": 1.0219,
          "CT": 0.0006,
          "CP": 0.0258,
          "eta": 0.0229
        },
        {
          "kind": "dynamic",
          "rpm": 8067.0,
          "J": 1.0619,
          "CT": -0.0077,
          "CP": 0.019,
          "eta": -0.4293
        },
        {
          "kind": "dynamic",
          "rpm": 8067.0,
          "J": 1.1042,
          "CT": -0.0166,
          "CP": 0.0102,
          "eta": -1.7997
        },
        {
          "kind": "dynamic",
          "rpm": 10042.0,
          "J": 0.069,
          "CT": 0.1333,
          "CP": 0.1125,
          "eta": 0.0818
        },
        {
          "kind": "dynamic",
          "rpm": 10042.0,
          "J": 0.1025,
          "CT": 0.1309,
          "CP": 0.1111,
          "eta": 0.1207
        },
        {
          "kind": "dynamic",
          "rpm": 10042.0,
          "J": 0.1366,
          "CT": 0.1299,
          "CP": 0.1109,
          "eta": 0.1602
        },
        {
          "kind": "dynamic",
          "rpm": 10042.0,
          "J": 0.1706,
          "CT": 0.1274,
          "CP": 0.1094,
          "eta": 0.1987
        },
        {
          "kind": "dynamic",
          "rpm": 10042.0,
          "J": 0.2026,
          "CT": 0.1256,
          "CP": 0.108,
          "eta": 0.2358
        },
        {
          "kind": "dynamic",
          "rpm": 10042.0,
          "J": 0.2385,
          "CT": 0.125,
          "CP": 0.1075,
          "eta": 0.2774
        },
        {
          "kind": "dynamic",
          "rpm": 10042.0,
          "J": 0.2699,
          "CT": 0.121,
          "CP": 0.1043,
          "eta": 0.313
        },
        {
          "kind": "dynamic",
          "rpm": 10042.0,
          "J": 0.3055,
          "CT": 0.1184,
          "CP": 0.1028,
          "eta": 0.3517
        },
        {
          "kind": "dynamic",
          "rpm": 10042.0,
          "J": 0.3398,
          "CT": 0.1162,
          "CP": 0.1017,
          "eta": 0.3881
        },
        {
          "kind": "dynamic",
          "rpm": 10042.0,
          "J": 0.3736,
          "CT": 0.1131,
          "CP": 0.1,
          "eta": 0.4226
        },
        {
          "kind": "dynamic",
          "rpm": 10042.0,
          "J": 0.4088,
          "CT": 0.1103,
          "CP": 0.0988,
          "eta": 0.4561
        },
        {
          "kind": "dynamic",
          "rpm": 10042.0,
          "J": 0.4413,
          "CT": 0.1065,
          "CP": 0.097,
          "eta": 0.4844
        },
        {
          "kind": "dynamic",
          "rpm": 10042.0,
          "J": 0.4768,
          "CT": 0.1034,
          "CP": 0.096,
          "eta": 0.5139
        },
        {
          "kind": "dynamic",
          "rpm": 10042.0,
          "J": 0.5109,
          "CT": 0.0993,
          "CP": 0.0943,
          "eta": 0.538
        },
        {
          "kind": "dynamic",
          "rpm": 10042.0,
          "J": 0.5415,
          "CT": 0.0948,
          "CP": 0.0921,
          "eta": 0.5577
        },
        {
          "kind": "dynamic",
          "rpm": 10042.0,
          "J": 0.5793,
          "CT": 0.0896,
          "CP": 0.0898,
          "eta": 0.5783
        },
        {
          "kind": "dynamic",
          "rpm": 10042.0,
          "J": 0.6104,
          "CT": 0.0842,
          "CP": 0.0867,
          "eta": 0.5925
        },
        {
          "kind": "dynamic",
          "rpm": 10042.0,
          "J": 0.6456,
          "CT": 0.0787,
          "CP": 0.0836,
          "eta": 0.6076
        },
        {
          "kind": "dynamic",
          "rpm": 10042.0,
          "J": 0.6811,
          "CT": 0.0734,
          "CP": 0.0807,
          "eta": 0.6189
        },
        {
          "kind": "dynamic",
          "rpm": 10071.0,
          "J": 0.5785,
          "CT": 0.0887,
          "CP": 0.089,
          "eta": 0.5768
        },
        {
          "kind": "dynamic",
          "rpm": 10071.0,
          "J": 0.6151,
          "CT": 0.0837,
          "CP": 0.0863,
          "eta": 0.5966
        },
        {
          "kind": "dynamic",
          "rpm": 10071.0,
          "J": 0.6468,
          "CT": 0.0781,
          "CP": 0.0831,
          "eta": 0.6078
        },
        {
          "kind": "dynamic",
          "rpm": 10071.0,
          "J": 0.681,
          "CT": 0.0729,
          "CP": 0.0801,
          "eta": 0.6201
        },
        {
          "kind": "dynamic",
          "rpm": 10071.0,
          "J": 0.7138,
          "CT": 0.0673,
          "CP": 0.0765,
          "eta": 0.6273
        },
        {
          "kind": "dynamic",
          "rpm": 10071.0,
          "J": 0.749,
          "CT": 0.0607,
          "CP": 0.0723,
          "eta": 0.6292
        },
        {
          "kind": "dynamic",
          "rpm": 10071.0,
          "J": 0.7797,
          "CT": 0.0537,
          "CP": 0.0672,
          "eta": 0.6233
        },
        {
          "kind": "dynamic",
          "rpm": 10071.0,
          "J": 0.8143,
          "CT": 0.0469,
          "CP": 0.062,
          "eta": 0.6154
        },
        {
          "kind": "dynamic",
          "rpm": 10071.0,
          "J": 0.853,
          "CT": 0.0391,
          "CP": 0.0561,
          "eta": 0.5949
        },
        {
          "kind": "dynamic",
          "rpm": 10071.0,
          "J": 0.8853,
          "CT": 0.0319,
          "CP": 0.0502,
          "eta": 0.5638
        },
        {
          "kind": "dynamic",
          "rpm": 10071.0,
          "J": 0.9203,
          "CT": 0.024,
          "CP": 0.0436,
          "eta": 0.5061
        },
        {
          "kind": "dynamic",
          "rpm": 10071.0,
          "J": 0.9534,
          "CT": 0.0169,
          "CP": 0.0378,
          "eta": 0.4268
        },
        {
          "kind": "dynamic",
          "rpm": 10071.0,
          "J": 0.9842,
          "CT": 0.0103,
          "CP": 0.0326,
          "eta": 0.3109
        },
        {
          "kind": "dynamic",
          "rpm": 10071.0,
          "J": 1.0228,
          "CT": 0.0018,
          "CP": 0.0254,
          "eta": 0.0733
        },
        {
          "kind": "dynamic",
          "rpm": 10071.0,
          "J": 1.0514,
          "CT": -0.0043,
          "CP": 0.02,
          "eta": -0.2236
        },
        {
          "kind": "dynamic",
          "rpm": 10071.0,
          "J": 1.0898,
          "CT": -0.0121,
          "CP": 0.0129,
          "eta": -1.0156
        },
        {
          "kind": "dynamic",
          "rpm": 10071.0,
          "J": 1.123,
          "CT": -0.0195,
          "CP": 0.0064,
          "eta": -3.4376
        },
        {
          "kind": "static",
          "rpm": 1490.0,
          "J": 0.0,
          "CT": 0.1251,
          "CP": 0.1354,
          "eta": 0.0
        },
        {
          "kind": "static",
          "rpm": 2033.0,
          "J": 0.0,
          "CT": 0.1219,
          "CP": 0.1263,
          "eta": 0.0
        },
        {
          "kind": "static",
          "rpm": 2556.0,
          "J": 0.0,
          "CT": 0.1216,
          "CP": 0.1181,
          "eta": 0.0
        },
        {
          "kind": "static",
          "rpm": 2946.0,
          "J": 0.0,
          "CT": 0.128,
          "CP": 0.1159,
          "eta": 0.0
        },
        {
          "kind": "static",
          "rpm": 3536.0,
          "J": 0.0,
          "CT": 0.1274,
          "CP": 0.1135,
          "eta": 0.0
        },
        {
          "kind": "static",
          "rpm": 4006.0,
          "J": 0.0,
          "CT": 0.1259,
          "CP": 0.1106,
          "eta": 0.0
        },
        {
          "kind": "static",
          "rpm": 4563.0,
          "J": 0.0,
          "CT": 0.1284,
          "CP": 0.1092,
          "eta": 0.0
        },
        {
          "kind": "static",
          "rpm": 4990.0,
          "J": 0.0,
          "CT": 0.127,
          "CP": 0.1144,
          "eta": 0.0
        },
        {
          "kind": "static",
          "rpm": 5463.0,
          "J": 0.0,
          "CT": 0.1286,
          "CP": 0.1117,
          "eta": 0.0
        },
        {
          "kind": "static",
          "rpm": 6003.0,
          "J": 0.0,
          "CT": 0.129,
          "CP": 0.1101,
          "eta": 0.0
        },
        {
          "kind": "static",
          "rpm": 6423.0,
          "J": 0.0,
          "CT": 0.1275,
          "CP": 0.1076,
          "eta": 0.0
        },
        {
          "kind": "static",
          "rpm": 6946.0,
          "J": 0.0,
          "CT": 0.1288,
          "CP": 0.1081,
          "eta": 0.0
        },
        {
          "kind": "static",
          "rpm": 7456.0,
          "J": 0.0,
          "CT": 0.1292,
          "CP": 0.1087,
          "eta": 0.0
        },
        {
          "kind": "static",
          "rpm": 7793.0,
          "J": 0.0,
          "CT": 0.1313,
          "CP": 0.1103,
          "eta": 0.0
        },
        {
          "kind": "static",
          "rpm": 8466.0,
          "J": 0.0,
          "CT": 0.1295,
          "CP": 0.1087,
          "eta": 0.0
        },
        {
          "kind": "static",
          "rpm": 8846.0,
          "J": 0.0,
          "CT": 0.1317,
          "CP": 0.1118,
          "eta": 0.0
        },
        {
          "kind": "static",
          "rpm": 9413.0,
          "J": 0.0,
          "CT": 0.133,
          "CP": 0.1108,
          "eta": 0.0
        },
        {
          "kind": "static",
          "rpm": 9880.0,
          "J": 0.0,
          "CT": 0.1292,
          "CP": 0.107,
          "eta": 0.0
        }
      ]
    }
  }
}